{
	"14栋": [
		{
			"roomFh": "'1-101'",
			"roomSzc": "1",
			"roomGpdj": "5000",
			"roomGpshdj": "0",
			"roomJzmj": "22.98",
			"roomTnjzmj": "22.32",
			"roomFtmj": "0.66",
			"dj": "0"
		},
		{
			"roomFh": "'1-102'",
			"roomSzc": "1",
			"roomGpdj": "5000",
			"roomGpshdj": "0",
			"roomJzmj": "26.8",
			"roomTnjzmj": "26.04",
			"roomFtmj": "0.76",
			"dj": "0"
		},
		{
			"roomFh": "'1-103'",
			"roomSzc": "1",
			"roomGpdj": "5000",
			"roomGpshdj": "0",
			"roomJzmj": "20.42",
			"roomTnjzmj": "19.84",
			"roomFtmj": "0.58",
			"dj": "0"
		},
		{
			"roomFh": "'1-104'",
			"roomSzc": "1",
			"roomGpdj": "5000",
			"roomGpshdj": "0",
			"roomJzmj": "25.52",
			"roomTnjzmj": "24.8",
			"roomFtmj": "0.72",
			"dj": "0"
		},
		{
			"roomFh": "'1-105'",
			"roomSzc": "1",
			"roomGpdj": "5000",
			"roomGpshdj": "0",
			"roomJzmj": "22.98",
			"roomTnjzmj": "22.32",
			"roomFtmj": "0.66",
			"dj": "0"
		},
		{
			"roomFh": "'1-111'",
			"roomSzc": "1",
			"roomGpdj": "5000",
			"roomGpshdj": "0",
			"roomJzmj": "17.41",
			"roomTnjzmj": "16.92",
			"roomFtmj": "0.49",
			"dj": "0"
		},
		{
			"roomFh": "'1-112'",
			"roomSzc": "1",
			"roomGpdj": "5000",
			"roomGpshdj": "0",
			"roomJzmj": "13.54",
			"roomTnjzmj": "13.16",
			"roomFtmj": "0.38",
			"dj": "0"
		},
		{
			"roomFh": "'1-113'",
			"roomSzc": "1",
			"roomGpdj": "5000",
			"roomGpshdj": "0",
			"roomJzmj": "11.11",
			"roomTnjzmj": "10.8",
			"roomFtmj": "0.31",
			"dj": "0"
		},
		{
			"roomFh": "'1-114'",
			"roomSzc": "1",
			"roomGpdj": "5000",
			"roomGpshdj": "0",
			"roomJzmj": "15.96",
			"roomTnjzmj": "15.51",
			"roomFtmj": "0.45",
			"dj": "0"
		},
		{
			"roomFh": "'1-115'",
			"roomSzc": "1",
			"roomGpdj": "5000",
			"roomGpshdj": "0",
			"roomJzmj": "17.67",
			"roomTnjzmj": "17.17",
			"roomFtmj": "0.5",
			"dj": "0"
		},
		{
			"roomFh": "'2-106'",
			"roomSzc": "1",
			"roomGpdj": "5000",
			"roomGpshdj": "0",
			"roomJzmj": "22.98",
			"roomTnjzmj": "22.32",
			"roomFtmj": "0.66",
			"dj": "0"
		},
		{
			"roomFh": "'2-107'",
			"roomSzc": "1",
			"roomGpdj": "5000",
			"roomGpshdj": "0",
			"roomJzmj": "25.52",
			"roomTnjzmj": "24.8",
			"roomFtmj": "0.72",
			"dj": "0"
		},
		{
			"roomFh": "'2-108'",
			"roomSzc": "1",
			"roomGpdj": "5000",
			"roomGpshdj": "0",
			"roomJzmj": "20.42",
			"roomTnjzmj": "19.84",
			"roomFtmj": "0.58",
			"dj": "0"
		},
		{
			"roomFh": "'2-109'",
			"roomSzc": "1",
			"roomHtbah": "'361026202300663'",
			"roomGpdj": "5000",
			"roomGpshdj": "0",
			"roomJzmj": "26.8",
			"roomTnjzmj": "26.04",
			"roomFtmj": ".76",
			"dj": "2100"
		},
		{
			"roomFh": "'2-110'",
			"roomSzc": "1",
			"roomGpdj": "5000",
			"roomGpshdj": "0",
			"roomJzmj": "22.98",
			"roomTnjzmj": "22.32",
			"roomFtmj": "0.66",
			"dj": "0"
		},
		{
			"roomFh": "'2-116'",
			"roomSzc": "1",
			"roomGpdj": "5000",
			"roomGpshdj": "0",
			"roomJzmj": "17.67",
			"roomTnjzmj": "17.17",
			"roomFtmj": "0.5",
			"dj": "0"
		},
		{
			"roomFh": "'2-117'",
			"roomSzc": "1",
			"roomGpdj": "5000",
			"roomGpshdj": "0",
			"roomJzmj": "15.96",
			"roomTnjzmj": "15.51",
			"roomFtmj": "0.45",
			"dj": "0"
		},
		{
			"roomFh": "'2-118'",
			"roomSzc": "1",
			"roomGpdj": "5000",
			"roomGpshdj": "0",
			"roomJzmj": "11.11",
			"roomTnjzmj": "10.8",
			"roomFtmj": "0.31",
			"dj": "0"
		},
		{
			"roomFh": "'2-119'",
			"roomSzc": "1",
			"roomGpdj": "5000",
			"roomGpshdj": "0",
			"roomJzmj": "13.54",
			"roomTnjzmj": "13.16",
			"roomFtmj": "0.38",
			"dj": "0"
		},
		{
			"roomFh": "'2-120'",
			"roomSzc": "1",
			"roomGpdj": "5000",
			"roomGpshdj": "0",
			"roomJzmj": "17.41",
			"roomTnjzmj": "16.92",
			"roomFtmj": "0.49",
			"dj": "0"
		},
		{
			"roomFh": "'1-201'",
			"roomSzc": "2",
			"roomSzdy": "'1'",
			"roomHtbah": "'361026202200146'",
			"roomGpdj": "2520",
			"roomGpshdj": "0",
			"roomJzmj": "123.97",
			"roomTnjzmj": "107.77",
			"roomFtmj": "16.2",
			"dj": "2171.99"
		},
		{
			"roomFh": "'1-202'",
			"roomSzc": "2",
			"roomSzdy": "'1'",
			"roomHtbah": "'361026202200215'",
			"roomGpdj": "2520",
			"roomGpshdj": "0",
			"roomJzmj": "93.2",
			"roomTnjzmj": "81.02",
			"roomFtmj": "12.18",
			"dj": "2171.98"
		},
		{
			"roomFh": "'2-203'",
			"roomSzc": "2",
			"roomSzdy": "'2'",
			"roomHtbah": "'361026202200207'",
			"roomGpdj": "2520",
			"roomGpshdj": "0",
			"roomJzmj": "93.2",
			"roomTnjzmj": "81.02",
			"roomFtmj": "12.18",
			"dj": "2171.98"
		},
		{
			"roomFh": "'2-204'",
			"roomSzc": "2",
			"roomSzdy": "'2'",
			"roomHtbah": "'361026202200140'",
			"roomGpdj": "2520",
			"roomGpshdj": "0",
			"roomJzmj": "123.97",
			"roomTnjzmj": "107.77",
			"roomFtmj": "16.2",
			"dj": "2171.99"
		},
		{
			"roomFh": "'1-301'",
			"roomSzc": "3",
			"roomSzdy": "'1'",
			"roomHtbah": "'361026202200145'",
			"roomGpdj": "2680",
			"roomGpshdj": "0",
			"roomJzmj": "123.97",
			"roomTnjzmj": "107.77",
			"roomFtmj": "16.2",
			"dj": "2171.99"
		},
		{
			"roomFh": "'1-302'",
			"roomSzc": "3",
			"roomSzdy": "'1'",
			"roomHtbah": "'361026202200214'",
			"roomGpdj": "2680",
			"roomGpshdj": "0",
			"roomJzmj": "93.2",
			"roomTnjzmj": "81.02",
			"roomFtmj": "12.18",
			"dj": "2171.98"
		},
		{
			"roomFh": "'2-303'",
			"roomSzc": "3",
			"roomSzdy": "'2'",
			"roomHtbah": "'361026202200206'",
			"roomGpdj": "2680",
			"roomGpshdj": "0",
			"roomJzmj": "93.2",
			"roomTnjzmj": "81.02",
			"roomFtmj": "12.18",
			"dj": "2171.98"
		},
		{
			"roomFh": "'2-304'",
			"roomSzc": "3",
			"roomSzdy": "'2'",
			"roomHtbah": "'361026202200139'",
			"roomGpdj": "2680",
			"roomGpshdj": "0",
			"roomJzmj": "123.97",
			"roomTnjzmj": "107.77",
			"roomFtmj": "16.2",
			"dj": "2171.99"
		},
		{
			"roomFh": "'1-401'",
			"roomSzc": "4",
			"roomSzdy": "'1'",
			"roomHtbah": "'361026202200144'",
			"roomGpdj": "2680",
			"roomGpshdj": "0",
			"roomJzmj": "123.97",
			"roomTnjzmj": "107.77",
			"roomFtmj": "16.2",
			"dj": "2171.99"
		},
		{
			"roomFh": "'1-402'",
			"roomSzc": "4",
			"roomSzdy": "'1'",
			"roomHtbah": "'361026202200210'",
			"roomGpdj": "2680",
			"roomGpshdj": "0",
			"roomJzmj": "93.2",
			"roomTnjzmj": "81.02",
			"roomFtmj": "12.18",
			"dj": "2171.98"
		},
		{
			"roomFh": "'2-403'",
			"roomSzc": "4",
			"roomSzdy": "'2'",
			"roomHtbah": "'361026202200142'",
			"roomGpdj": "2680",
			"roomGpshdj": "0",
			"roomJzmj": "93.2",
			"roomTnjzmj": "81.02",
			"roomFtmj": "12.18",
			"dj": "2171.98"
		},
		{
			"roomFh": "'2-404'",
			"roomSzc": "4",
			"roomSzdy": "'2'",
			"roomGpdj": "2680",
			"roomGpshdj": "0",
			"roomJzmj": "123.97",
			"roomTnjzmj": "107.77",
			"roomFtmj": "16.2",
			"dj": "2171.99"
		},
		{
			"roomFh": "'1-501'",
			"roomSzc": "5",
			"roomSzdy": "'1'",
			"roomHtbah": "'361026202200143'",
			"roomGpdj": "2520",
			"roomGpshdj": "0",
			"roomJzmj": "123.97",
			"roomTnjzmj": "107.77",
			"roomFtmj": "16.2",
			"dj": "2171.99"
		},
		{
			"roomFh": "'1-502'",
			"roomSzc": "5",
			"roomSzdy": "'1'",
			"roomHtbah": "'361026202200209'",
			"roomGpdj": "2520",
			"roomGpshdj": "0",
			"roomJzmj": "93.2",
			"roomTnjzmj": "81.02",
			"roomFtmj": "12.18",
			"dj": "2171.98"
		},
		{
			"roomFh": "'2-503'",
			"roomSzc": "5",
			"roomSzdy": "'2'",
			"roomHtbah": "'361026202200141'",
			"roomGpdj": "2520",
			"roomGpshdj": "0",
			"roomJzmj": "93.2",
			"roomTnjzmj": "81.02",
			"roomFtmj": "12.18",
			"dj": "2171.98"
		},
		{
			"roomFh": "'2-504'",
			"roomSzc": "5",
			"roomSzdy": "'2'",
			"roomHtbah": "'361026202200138'",
			"roomGpdj": "2520",
			"roomGpshdj": "0",
			"roomJzmj": "123.97",
			"roomTnjzmj": "107.77",
			"roomFtmj": "16.2",
			"dj": "2171.99"
		}
	],
	"15栋": [
		{
			"roomFh": "'1-101'",
			"roomSzc": "1",
			"roomGpdj": "5000",
			"roomGpshdj": "0",
			"roomJzmj": "22.98",
			"roomTnjzmj": "22.32",
			"roomFtmj": "0.66",
			"dj": "0"
		},
		{
			"roomFh": "'1-102'",
			"roomSzc": "1",
			"roomGpdj": "5000",
			"roomGpshdj": "0",
			"roomJzmj": "26.8",
			"roomTnjzmj": "26.04",
			"roomFtmj": "0.76",
			"dj": "0"
		},
		{
			"roomFh": "'1-103'",
			"roomSzc": "1",
			"roomGpdj": "5000",
			"roomGpshdj": "0",
			"roomJzmj": "20.42",
			"roomTnjzmj": "19.84",
			"roomFtmj": "0.58",
			"dj": "0"
		},
		{
			"roomFh": "'1-104'",
			"roomSzc": "1",
			"roomGpdj": "5000",
			"roomGpshdj": "0",
			"roomJzmj": "25.52",
			"roomTnjzmj": "24.8",
			"roomFtmj": "0.72",
			"dj": "0"
		},
		{
			"roomFh": "'1-105'",
			"roomSzc": "1",
			"roomGpdj": "5000",
			"roomGpshdj": "0",
			"roomJzmj": "22.98",
			"roomTnjzmj": "22.32",
			"roomFtmj": "0.66",
			"dj": "0"
		},
		{
			"roomFh": "'1-111'",
			"roomSzc": "1",
			"roomGpdj": "5000",
			"roomGpshdj": "0",
			"roomJzmj": "17.41",
			"roomTnjzmj": "16.92",
			"roomFtmj": "0.49",
			"dj": "0"
		},
		{
			"roomFh": "'1-112'",
			"roomSzc": "1",
			"roomGpdj": "5000",
			"roomGpshdj": "0",
			"roomJzmj": "13.54",
			"roomTnjzmj": "13.16",
			"roomFtmj": "0.38",
			"dj": "0"
		},
		{
			"roomFh": "'1-113'",
			"roomSzc": "1",
			"roomGpdj": "5000",
			"roomGpshdj": "0",
			"roomJzmj": "11.11",
			"roomTnjzmj": "10.8",
			"roomFtmj": "0.31",
			"dj": "0"
		},
		{
			"roomFh": "'1-114'",
			"roomSzc": "1",
			"roomGpdj": "5000",
			"roomGpshdj": "0",
			"roomJzmj": "15.96",
			"roomTnjzmj": "15.51",
			"roomFtmj": "0.45",
			"dj": "0"
		},
		{
			"roomFh": "'1-115'",
			"roomSzc": "1",
			"roomGpdj": "5000",
			"roomGpshdj": "0",
			"roomJzmj": "17.67",
			"roomTnjzmj": "17.17",
			"roomFtmj": "0.5",
			"dj": "0"
		},
		{
			"roomFh": "'2-106'",
			"roomSzc": "1",
			"roomGpdj": "5000",
			"roomGpshdj": "0",
			"roomJzmj": "22.98",
			"roomTnjzmj": "22.32",
			"roomFtmj": "0.66",
			"dj": "0"
		},
		{
			"roomFh": "'2-107'",
			"roomSzc": "1",
			"roomGpdj": "5000",
			"roomGpshdj": "0",
			"roomJzmj": "25.52",
			"roomTnjzmj": "24.8",
			"roomFtmj": "0.72",
			"dj": "0"
		},
		{
			"roomFh": "'2-108'",
			"roomSzc": "1",
			"roomGpdj": "5000",
			"roomGpshdj": "0",
			"roomJzmj": "20.42",
			"roomTnjzmj": "19.84",
			"roomFtmj": "0.58",
			"dj": "0"
		},
		{
			"roomFh": "'2-109'",
			"roomSzc": "1",
			"roomGpdj": "5000",
			"roomGpshdj": "0",
			"roomJzmj": "26.8",
			"roomTnjzmj": "26.04",
			"roomFtmj": "0.76",
			"dj": "0"
		},
		{
			"roomFh": "'2-110'",
			"roomSzc": "1",
			"roomGpdj": "5000",
			"roomGpshdj": "0",
			"roomJzmj": "22.98",
			"roomTnjzmj": "22.32",
			"roomFtmj": "0.66",
			"dj": "0"
		},
		{
			"roomFh": "'2-116'",
			"roomSzc": "1",
			"roomGpdj": "5000",
			"roomGpshdj": "0",
			"roomJzmj": "17.67",
			"roomTnjzmj": "17.17",
			"roomFtmj": "0.5",
			"dj": "0"
		},
		{
			"roomFh": "'2-117'",
			"roomSzc": "1",
			"roomGpdj": "5000",
			"roomGpshdj": "0",
			"roomJzmj": "15.96",
			"roomTnjzmj": "15.51",
			"roomFtmj": "0.45",
			"dj": "0"
		},
		{
			"roomFh": "'2-118'",
			"roomSzc": "1",
			"roomGpdj": "5000",
			"roomGpshdj": "0",
			"roomJzmj": "11.11",
			"roomTnjzmj": "10.8",
			"roomFtmj": "0.31",
			"dj": "0"
		},
		{
			"roomFh": "'2-119'",
			"roomSzc": "1",
			"roomGpdj": "5000",
			"roomGpshdj": "0",
			"roomJzmj": "13.54",
			"roomTnjzmj": "13.16",
			"roomFtmj": "0.38",
			"dj": "0"
		},
		{
			"roomFh": "'2-120'",
			"roomSzc": "1",
			"roomGpdj": "5000",
			"roomGpshdj": "0",
			"roomJzmj": "17.41",
			"roomTnjzmj": "16.92",
			"roomFtmj": "0.49",
			"dj": "0"
		},
		{
			"roomFh": "'1-201'",
			"roomSzc": "2",
			"roomSzdy": "'1'",
			"roomGpdj": "2520",
			"roomGpshdj": "0",
			"roomJzmj": "123.97",
			"roomTnjzmj": "107.77",
			"roomFtmj": "16.2",
			"dj": "0"
		},
		{
			"roomFh": "'1-202'",
			"roomSzc": "2",
			"roomSzdy": "'1'",
			"roomHtbah": "'361026202200016'",
			"roomGpdj": "2520",
			"roomGpshdj": "0",
			"roomJzmj": "93.2",
			"roomTnjzmj": "81.02",
			"roomFtmj": "12.18",
			"dj": "1321.2"
		},
		{
			"roomFh": "'2-203'",
			"roomSzc": "2",
			"roomSzdy": "'2'",
			"roomHtbah": "'361026202200111'",
			"roomGpdj": "2520",
			"roomGpshdj": "0",
			"roomJzmj": "93.2",
			"roomTnjzmj": "81.02",
			"roomFtmj": "12.18",
			"dj": "2171.98"
		},
		{
			"roomFh": "'2-204'",
			"roomSzc": "2",
			"roomSzdy": "'2'",
			"roomGpdj": "2520",
			"roomGpshdj": "0",
			"roomJzmj": "123.97",
			"roomTnjzmj": "107.77",
			"roomFtmj": "16.2",
			"dj": "0"
		},
		{
			"roomFh": "'1-301'",
			"roomSzc": "3",
			"roomSzdy": "'1'",
			"roomGpdj": "2680",
			"roomGpshdj": "0",
			"roomJzmj": "123.97",
			"roomTnjzmj": "107.77",
			"roomFtmj": "16.2",
			"dj": "0"
		},
		{
			"roomFh": "'1-302'",
			"roomSzc": "3",
			"roomSzdy": "'1'",
			"roomHtbah": "'361026202200017'",
			"roomGpdj": "2680",
			"roomGpshdj": "0",
			"roomJzmj": "93.2",
			"roomTnjzmj": "81.02",
			"roomFtmj": "12.18",
			"dj": "1321.2"
		},
		{
			"roomFh": "'2-303'",
			"roomSzc": "3",
			"roomSzdy": "'2'",
			"roomHtbah": "'361026202200014'",
			"roomGpdj": "2680",
			"roomGpshdj": "0",
			"roomJzmj": "93.2",
			"roomTnjzmj": "81.02",
			"roomFtmj": "12.18",
			"dj": "1321.2"
		},
		{
			"roomFh": "'2-304'",
			"roomSzc": "3",
			"roomSzdy": "'2'",
			"roomHtbah": "'361026202200106'",
			"roomGpdj": "2680",
			"roomGpshdj": "0",
			"roomJzmj": "123.97",
			"roomTnjzmj": "107.77",
			"roomFtmj": "16.2",
			"dj": "2171.99"
		},
		{
			"roomFh": "'1-401'",
			"roomSzc": "4",
			"roomSzdy": "'1'",
			"roomHtbah": "'361026202200108'",
			"roomGpdj": "2680",
			"roomGpshdj": "0",
			"roomJzmj": "123.97",
			"roomTnjzmj": "107.77",
			"roomFtmj": "16.2",
			"dj": "2171.99"
		},
		{
			"roomFh": "'1-402'",
			"roomSzc": "4",
			"roomSzdy": "'1'",
			"roomHtbah": "'361026202200021'",
			"roomGpdj": "2680",
			"roomGpshdj": "0",
			"roomJzmj": "93.2",
			"roomTnjzmj": "81.02",
			"roomFtmj": "12.18",
			"dj": "1321.2"
		},
		{
			"roomFh": "'2-403'",
			"roomSzc": "4",
			"roomSzdy": "'2'",
			"roomHtbah": "'361026202200015'",
			"roomGpdj": "2680",
			"roomGpshdj": "0",
			"roomJzmj": "93.2",
			"roomTnjzmj": "81.02",
			"roomFtmj": "12.18",
			"dj": "1321.2"
		},
		{
			"roomFh": "'2-404'",
			"roomSzc": "4",
			"roomSzdy": "'2'",
			"roomHtbah": "'361026202200105'",
			"roomGpdj": "2680",
			"roomGpshdj": "0",
			"roomJzmj": "123.97",
			"roomTnjzmj": "107.77",
			"roomFtmj": "16.2",
			"dj": "2171.99"
		},
		{
			"roomFh": "'1-501'",
			"roomSzc": "5",
			"roomSzdy": "'1'",
			"roomHtbah": "'361026202200107'",
			"roomGpdj": "2520",
			"roomGpshdj": "0",
			"roomJzmj": "123.97",
			"roomTnjzmj": "107.77",
			"roomFtmj": "16.2",
			"dj": "2171.99"
		},
		{
			"roomFh": "'1-502'",
			"roomSzc": "5",
			"roomSzdy": "'1'",
			"roomHtbah": "'361026202200019'",
			"roomGpdj": "2520",
			"roomGpshdj": "0",
			"roomJzmj": "93.2",
			"roomTnjzmj": "81.02",
			"roomFtmj": "12.18",
			"dj": "1321.2"
		},
		{
			"roomFh": "'2-503'",
			"roomSzc": "5",
			"roomSzdy": "'2'",
			"roomHtbah": "'361026202200020'",
			"roomGpdj": "2520",
			"roomGpshdj": "0",
			"roomJzmj": "93.2",
			"roomTnjzmj": "81.02",
			"roomFtmj": "12.18",
			"dj": "1321.2"
		},
		{
			"roomFh": "'2-504'",
			"roomSzc": "5",
			"roomSzdy": "'2'",
			"roomHtbah": "'361026202200104'",
			"roomGpdj": "2520",
			"roomGpshdj": "0",
			"roomJzmj": "123.97",
			"roomTnjzmj": "107.77",
			"roomFtmj": "16.2",
			"dj": "2171.99"
		}
	],
	"23栋": [
		{
			"roomFh": "'2-106'",
			"roomSzc": "1",
			"roomSzdy": "'0'",
			"roomGpdj": "0",
			"roomGpshdj": "0",
			"roomJzmj": "21.73",
			"roomTnjzmj": "21.08",
			"roomFtmj": "0.65",
			"dj": "0"
		},
		{
			"roomFh": "'2-107'",
			"roomSzc": "1",
			"roomSzdy": "'0'",
			"roomGpdj": "0",
			"roomGpshdj": "0",
			"roomJzmj": "24.28",
			"roomTnjzmj": "23.56",
			"roomFtmj": "0.72",
			"dj": "0"
		},
		{
			"roomFh": "'2-108'",
			"roomSzc": "1",
			"roomSzdy": "'0'",
			"roomGpdj": "0",
			"roomGpshdj": "0",
			"roomJzmj": "16.61",
			"roomTnjzmj": "16.12",
			"roomFtmj": "0.49",
			"dj": "0"
		},
		{
			"roomFh": "'1-103'",
			"roomSzc": "1",
			"roomSzdy": "'1'",
			"roomGpdj": "5000",
			"roomGpshdj": "0",
			"roomJzmj": "16.61",
			"roomTnjzmj": "16.12",
			"roomFtmj": "0.49",
			"dj": "0"
		},
		{
			"roomFh": "'1-104'",
			"roomSzc": "1",
			"roomSzdy": "'1'",
			"roomGpdj": "0",
			"roomGpshdj": "0",
			"roomJzmj": "24.28",
			"roomTnjzmj": "23.56",
			"roomFtmj": "0.72",
			"dj": "0"
		},
		{
			"roomFh": "'1-105'",
			"roomSzc": "1",
			"roomSzdy": "'1'",
			"roomGpdj": "0",
			"roomGpshdj": "0",
			"roomJzmj": "22.37",
			"roomTnjzmj": "21.7",
			"roomFtmj": "0.67",
			"dj": "0"
		},
		{
			"roomFh": "'1-101'",
			"roomSzc": "1",
			"roomHtbah": "'361026202200121'",
			"roomGpdj": "5000",
			"roomGpshdj": "0",
			"roomJzmj": "21.09",
			"roomTnjzmj": "20.46",
			"roomFtmj": "0.63",
			"dj": "1683.69"
		},
		{
			"roomFh": "'1-102'",
			"roomSzc": "1",
			"roomHtbah": "'361026202200122'",
			"roomGpdj": "5000",
			"roomGpshdj": "0",
			"roomJzmj": "24.28",
			"roomTnjzmj": "23.56",
			"roomFtmj": "0.72",
			"dj": "1683.69"
		},
		{
			"roomFh": "'1-121'",
			"roomSzc": "1",
			"roomGpdj": "5000",
			"roomGpshdj": "0",
			"roomJzmj": "15.99",
			"roomTnjzmj": "15.51",
			"roomFtmj": "0.48",
			"dj": "0"
		},
		{
			"roomFh": "'1-122'",
			"roomSzc": "1",
			"roomGpdj": "5000",
			"roomGpshdj": "0",
			"roomJzmj": "18.41",
			"roomTnjzmj": "17.86",
			"roomFtmj": "0.55",
			"dj": "0"
		},
		{
			"roomFh": "'1-123'",
			"roomSzc": "1",
			"roomGpdj": "5000",
			"roomGpshdj": "0",
			"roomJzmj": "15.02",
			"roomTnjzmj": "14.57",
			"roomFtmj": "0.45",
			"dj": "0"
		},
		{
			"roomFh": "'1-124'",
			"roomSzc": "1",
			"roomGpdj": "5000",
			"roomGpshdj": "0",
			"roomJzmj": "17.21",
			"roomTnjzmj": "16.7",
			"roomFtmj": "0.51",
			"dj": "0"
		},
		{
			"roomFh": "'2-109'",
			"roomSzc": "1",
			"roomHtbah": "'361026202200123'",
			"roomGpdj": "5000",
			"roomGpshdj": "0",
			"roomJzmj": "20.45",
			"roomTnjzmj": "19.84",
			"roomFtmj": "0.61",
			"dj": "1683.67"
		},
		{
			"roomFh": "'2-110'",
			"roomSzc": "1",
			"roomHtbah": "'361026202200124'",
			"roomGpdj": "5000",
			"roomGpshdj": "0",
			"roomJzmj": "19.81",
			"roomTnjzmj": "19.22",
			"roomFtmj": "0.59",
			"dj": "1683.7"
		},
		{
			"roomFh": "'2-125'",
			"roomSzc": "1",
			"roomGpdj": "5000",
			"roomGpshdj": "0",
			"roomJzmj": "16.73",
			"roomTnjzmj": "16.23",
			"roomFtmj": "0.5",
			"dj": "0"
		},
		{
			"roomFh": "'2-126'",
			"roomSzc": "1",
			"roomGpdj": "5000",
			"roomGpshdj": "0",
			"roomJzmj": "15.02",
			"roomTnjzmj": "14.57",
			"roomFtmj": "0.45",
			"dj": "0"
		},
		{
			"roomFh": "'2-127'",
			"roomSzc": "1",
			"roomGpdj": "5000",
			"roomGpshdj": "0",
			"roomJzmj": "12.11",
			"roomTnjzmj": "11.75",
			"roomFtmj": "0.36",
			"dj": "0"
		},
		{
			"roomFh": "'2-128'",
			"roomSzc": "1",
			"roomGpdj": "5000",
			"roomGpshdj": "0",
			"roomJzmj": "15.27",
			"roomTnjzmj": "14.82",
			"roomFtmj": "0.45",
			"dj": "0"
		},
		{
			"roomFh": "'3-111'",
			"roomSzc": "1",
			"roomHtbah": "'361026202200136'",
			"roomGpdj": "5000",
			"roomGpshdj": "0",
			"roomJzmj": "19.81",
			"roomTnjzmj": "19.22",
			"roomFtmj": "0.59",
			"dj": "1683.7"
		},
		{
			"roomFh": "'3-112'",
			"roomSzc": "1",
			"roomHtbah": "'361026202200125'",
			"roomGpdj": "5000",
			"roomGpshdj": "0",
			"roomJzmj": "20.45",
			"roomTnjzmj": "19.84",
			"roomFtmj": "0.61",
			"dj": "1683.67"
		},
		{
			"roomFh": "'3-113'",
			"roomSzc": "1",
			"roomHtbah": "'361026202200126'",
			"roomGpdj": "5000",
			"roomGpshdj": "0",
			"roomJzmj": "16.61",
			"roomTnjzmj": "16.12",
			"roomFtmj": "0.49",
			"dj": "1683.68"
		},
		{
			"roomFh": "'3-114'",
			"roomSzc": "1",
			"roomHtbah": "'361026202200135'",
			"roomGpdj": "5000",
			"roomGpshdj": "0",
			"roomJzmj": "24.28",
			"roomTnjzmj": "23.56",
			"roomFtmj": "0.72",
			"dj": "1683.69"
		},
		{
			"roomFh": "'3-115'",
			"roomSzc": "1",
			"roomHtbah": "'361026202200134'",
			"roomGpdj": "5000",
			"roomGpshdj": "0",
			"roomJzmj": "21.73",
			"roomTnjzmj": "21.08",
			"roomFtmj": "0.65",
			"dj": "1683.66"
		},
		{
			"roomFh": "'3-129'",
			"roomSzc": "1",
			"roomGpdj": "5000",
			"roomGpshdj": "0",
			"roomJzmj": "15.27",
			"roomTnjzmj": "14.82",
			"roomFtmj": "0.45",
			"dj": "0"
		},
		{
			"roomFh": "'3-130'",
			"roomSzc": "1",
			"roomGpdj": "5000",
			"roomGpshdj": "0",
			"roomJzmj": "12.11",
			"roomTnjzmj": "11.75",
			"roomFtmj": "0.36",
			"dj": "0"
		},
		{
			"roomFh": "'3-131'",
			"roomSzc": "1",
			"roomGpdj": "5000",
			"roomGpshdj": "0",
			"roomJzmj": "15.02",
			"roomTnjzmj": "14.57",
			"roomFtmj": "0.45",
			"dj": "0"
		},
		{
			"roomFh": "'3-132'",
			"roomSzc": "1",
			"roomGpdj": "5000",
			"roomGpshdj": "0",
			"roomJzmj": "16.73",
			"roomTnjzmj": "16.23",
			"roomFtmj": "0.5",
			"dj": "0"
		},
		{
			"roomFh": "'4-116'",
			"roomSzc": "1",
			"roomHtbah": "'361026202200133'",
			"roomGpdj": "5000",
			"roomGpshdj": "0",
			"roomJzmj": "22.37",
			"roomTnjzmj": "21.7",
			"roomFtmj": "0.67",
			"dj": "1683.68"
		},
		{
			"roomFh": "'4-117'",
			"roomSzc": "1",
			"roomHtbah": "'361026202200132'",
			"roomGpdj": "5000",
			"roomGpshdj": "0",
			"roomJzmj": "24.28",
			"roomTnjzmj": "23.56",
			"roomFtmj": "0.72",
			"dj": "1683.69"
		},
		{
			"roomFh": "'4-118'",
			"roomSzc": "1",
			"roomHtbah": "'361026202200131'",
			"roomGpdj": "5000",
			"roomGpshdj": "0",
			"roomJzmj": "16.61",
			"roomTnjzmj": "16.12",
			"roomFtmj": "0.49",
			"dj": "1683.68"
		},
		{
			"roomFh": "'4-119'",
			"roomSzc": "1",
			"roomHtbah": "'361026202200130'",
			"roomGpdj": "5000",
			"roomGpshdj": "0",
			"roomJzmj": "24.28",
			"roomTnjzmj": "23.56",
			"roomFtmj": "0.72",
			"dj": "1683.69"
		},
		{
			"roomFh": "'4-120'",
			"roomSzc": "1",
			"roomHtbah": "'361026202200129'",
			"roomGpdj": "5000",
			"roomGpshdj": "0",
			"roomJzmj": "21.09",
			"roomTnjzmj": "20.46",
			"roomFtmj": "0.63",
			"dj": "1683.69"
		},
		{
			"roomFh": "'4-133'",
			"roomSzc": "1",
			"roomGpdj": "5000",
			"roomGpshdj": "0",
			"roomJzmj": "17.21",
			"roomTnjzmj": "16.7",
			"roomFtmj": "0.51",
			"dj": "0"
		},
		{
			"roomFh": "'4-134'",
			"roomSzc": "1",
			"roomGpdj": "5000",
			"roomGpshdj": "0",
			"roomJzmj": "15.02",
			"roomTnjzmj": "14.57",
			"roomFtmj": "0.45",
			"dj": "0"
		},
		{
			"roomFh": "'4-135'",
			"roomSzc": "1",
			"roomGpdj": "5000",
			"roomGpshdj": "0",
			"roomJzmj": "18.41",
			"roomTnjzmj": "17.86",
			"roomFtmj": "0.55",
			"dj": "0"
		},
		{
			"roomFh": "'4-136'",
			"roomSzc": "1",
			"roomGpdj": "5000",
			"roomGpshdj": "0",
			"roomJzmj": "15.99",
			"roomTnjzmj": "15.51",
			"roomFtmj": "0.48",
			"dj": "0"
		},
		{
			"roomFh": "'1-201'",
			"roomSzc": "2",
			"roomSzdy": "'1'",
			"roomHtbah": "'361026202200160'",
			"roomGpdj": "2520",
			"roomGpshdj": "0",
			"roomJzmj": "108.15",
			"roomTnjzmj": "92.33",
			"roomFtmj": "15.82",
			"dj": "2171.99"
		},
		{
			"roomFh": "'1-202'",
			"roomSzc": "2",
			"roomSzdy": "'1'",
			"roomHtbah": "'361026202200025'",
			"roomGpdj": "2520",
			"roomGpshdj": "0",
			"roomJzmj": "91.11",
			"roomTnjzmj": "77.78",
			"roomFtmj": "13.33",
			"dj": "1321.21"
		},
		{
			"roomFh": "'2-203'",
			"roomSzc": "2",
			"roomSzdy": "'2'",
			"roomHtbah": "'361026202200170'",
			"roomGpdj": "2520",
			"roomGpshdj": "0",
			"roomJzmj": "104.14",
			"roomTnjzmj": "88.91",
			"roomFtmj": "15.23",
			"dj": "2171.99"
		},
		{
			"roomFh": "'2-204'",
			"roomSzc": "2",
			"roomSzdy": "'2'",
			"roomHtbah": "'361026202200159'",
			"roomGpdj": "2520",
			"roomGpshdj": "0",
			"roomJzmj": "78.45",
			"roomTnjzmj": "66.97",
			"roomFtmj": "11.48",
			"dj": "2171.99"
		},
		{
			"roomFh": "'3-205'",
			"roomSzc": "2",
			"roomSzdy": "'3'",
			"roomHtbah": "'361026202200153'",
			"roomGpdj": "2520",
			"roomGpshdj": "0",
			"roomJzmj": "78.45",
			"roomTnjzmj": "66.97",
			"roomFtmj": "11.48",
			"dj": "2171.99"
		},
		{
			"roomFh": "'3-206'",
			"roomSzc": "2",
			"roomSzdy": "'3'",
			"roomHtbah": "'361026202200149'",
			"roomGpdj": "2520",
			"roomGpshdj": "0",
			"roomJzmj": "104.14",
			"roomTnjzmj": "88.91",
			"roomFtmj": "15.23",
			"dj": "2171.99"
		},
		{
			"roomFh": "'4-207'",
			"roomSzc": "2",
			"roomSzdy": "'4'",
			"roomHtbah": "'361026202200022'",
			"roomGpdj": "2520",
			"roomGpshdj": "0",
			"roomJzmj": "91.11",
			"roomTnjzmj": "77.78",
			"roomFtmj": "13.33",
			"dj": "1321.21"
		},
		{
			"roomFh": "'4-208'",
			"roomSzc": "2",
			"roomSzdy": "'4'",
			"roomHtbah": "'361026202200118'",
			"roomGpdj": "2520",
			"roomGpshdj": "0",
			"roomJzmj": "108.15",
			"roomTnjzmj": "92.33",
			"roomFtmj": "15.82",
			"dj": "2171.99"
		},
		{
			"roomFh": "'1-301'",
			"roomSzc": "3",
			"roomSzdy": "'1'",
			"roomHtbah": "'361026202200161'",
			"roomGpdj": "2680",
			"roomGpshdj": "0",
			"roomJzmj": "108.15",
			"roomTnjzmj": "92.33",
			"roomFtmj": "15.82",
			"dj": "2171.99"
		},
		{
			"roomFh": "'1-302'",
			"roomSzc": "3",
			"roomSzdy": "'1'",
			"roomHtbah": "'361026202200026'",
			"roomGpdj": "2680",
			"roomGpshdj": "0",
			"roomJzmj": "91.11",
			"roomTnjzmj": "77.78",
			"roomFtmj": "13.33",
			"dj": "1321.21"
		},
		{
			"roomFh": "'2-303'",
			"roomSzc": "3",
			"roomSzdy": "'2'",
			"roomHtbah": "'361026202200166'",
			"roomGpdj": "2680",
			"roomGpshdj": "0",
			"roomJzmj": "104.14",
			"roomTnjzmj": "88.91",
			"roomFtmj": "15.23",
			"dj": "2171.99"
		},
		{
			"roomFh": "'2-304'",
			"roomSzc": "3",
			"roomSzdy": "'2'",
			"roomHtbah": "'361026202200192'",
			"roomGpdj": "2680",
			"roomGpshdj": "0",
			"roomJzmj": "78.45",
			"roomTnjzmj": "66.97",
			"roomFtmj": "11.48",
			"dj": "2171.99"
		},
		{
			"roomFh": "'3-305'",
			"roomSzc": "3",
			"roomSzdy": "'3'",
			"roomHtbah": "'361026202200152'",
			"roomGpdj": "2680",
			"roomGpshdj": "0",
			"roomJzmj": "78.45",
			"roomTnjzmj": "66.97",
			"roomFtmj": "11.48",
			"dj": "2171.99"
		},
		{
			"roomFh": "'3-306'",
			"roomSzc": "3",
			"roomSzdy": "'3'",
			"roomHtbah": "'361026202200148'",
			"roomGpdj": "2680",
			"roomGpshdj": "0",
			"roomJzmj": "104.14",
			"roomTnjzmj": "88.91",
			"roomFtmj": "15.23",
			"dj": "2171.99"
		},
		{
			"roomFh": "'4-307'",
			"roomSzc": "3",
			"roomSzdy": "'4'",
			"roomHtbah": "'361026202200018'",
			"roomGpdj": "2680",
			"roomGpshdj": "0",
			"roomJzmj": "91.11",
			"roomTnjzmj": "77.78",
			"roomFtmj": "13.33",
			"dj": "1321.21"
		},
		{
			"roomFh": "'4-308'",
			"roomSzc": "3",
			"roomSzdy": "'4'",
			"roomHtbah": "'361026202200114'",
			"roomGpdj": "2680",
			"roomGpshdj": "0",
			"roomJzmj": "108.15",
			"roomTnjzmj": "92.33",
			"roomFtmj": "15.82",
			"dj": "2171.99"
		},
		{
			"roomFh": "'1-401'",
			"roomSzc": "4",
			"roomSzdy": "'1'",
			"roomHtbah": "'361026202200229'",
			"roomGpdj": "2680",
			"roomGpshdj": "0",
			"roomJzmj": "108.15",
			"roomTnjzmj": "92.33",
			"roomFtmj": "15.82",
			"dj": "2171.99"
		},
		{
			"roomFh": "'1-402'",
			"roomSzc": "4",
			"roomSzdy": "'1'",
			"roomHtbah": "'361026202200027'",
			"roomGpdj": "2680",
			"roomGpshdj": "0",
			"roomJzmj": "91.11",
			"roomTnjzmj": "77.78",
			"roomFtmj": "13.33",
			"dj": "1321.21"
		},
		{
			"roomFh": "'2-403'",
			"roomSzc": "4",
			"roomSzdy": "'2'",
			"roomHtbah": "'361026202200168'",
			"roomGpdj": "2680",
			"roomGpshdj": "0",
			"roomJzmj": "104.14",
			"roomTnjzmj": "88.91",
			"roomFtmj": "15.23",
			"dj": "2171.99"
		},
		{
			"roomFh": "'2-404'",
			"roomSzc": "4",
			"roomSzdy": "'2'",
			"roomHtbah": "'361026202200157'",
			"roomGpdj": "2680",
			"roomGpshdj": "0",
			"roomJzmj": "78.45",
			"roomTnjzmj": "66.97",
			"roomFtmj": "11.48",
			"dj": "2171.99"
		},
		{
			"roomFh": "'3-405'",
			"roomSzc": "4",
			"roomSzdy": "'3'",
			"roomHtbah": "'361026202200151'",
			"roomGpdj": "2680",
			"roomGpshdj": "0",
			"roomJzmj": "78.45",
			"roomTnjzmj": "66.97",
			"roomFtmj": "11.48",
			"dj": "2171.99"
		},
		{
			"roomFh": "'3-406'",
			"roomSzc": "4",
			"roomSzdy": "'3'",
			"roomHtbah": "'361026202200220'",
			"roomGpdj": "2680",
			"roomGpshdj": "0",
			"roomJzmj": "104.14",
			"roomTnjzmj": "88.91",
			"roomFtmj": "15.23",
			"dj": "2171.99"
		},
		{
			"roomFh": "'4-407'",
			"roomSzc": "4",
			"roomSzdy": "'4'",
			"roomHtbah": "'361026202200023'",
			"roomGpdj": "2680",
			"roomGpshdj": "0",
			"roomJzmj": "91.11",
			"roomTnjzmj": "77.78",
			"roomFtmj": "13.33",
			"dj": "1321.21"
		},
		{
			"roomFh": "'4-408'",
			"roomSzc": "4",
			"roomSzdy": "'4'",
			"roomHtbah": "'361026202200113'",
			"roomGpdj": "2680",
			"roomGpshdj": "0",
			"roomJzmj": "108.15",
			"roomTnjzmj": "92.33",
			"roomFtmj": "15.82",
			"dj": "2171.99"
		},
		{
			"roomFh": "'1-501'",
			"roomSzc": "5",
			"roomSzdy": "'1'",
			"roomHtbah": "'361026202200163'",
			"roomGpdj": "2520",
			"roomGpshdj": "0",
			"roomJzmj": "108.15",
			"roomTnjzmj": "92.33",
			"roomFtmj": "15.82",
			"dj": "2171.99"
		},
		{
			"roomFh": "'1-502'",
			"roomSzc": "5",
			"roomSzdy": "'1'",
			"roomHtbah": "'361026202200028'",
			"roomGpdj": "2520",
			"roomGpshdj": "0",
			"roomJzmj": "91.11",
			"roomTnjzmj": "77.78",
			"roomFtmj": "13.33",
			"dj": "1321.21"
		},
		{
			"roomFh": "'2-503'",
			"roomSzc": "5",
			"roomSzdy": "'2'",
			"roomHtbah": "'361026202200162'",
			"roomGpdj": "2520",
			"roomGpshdj": "0",
			"roomJzmj": "104.14",
			"roomTnjzmj": "88.91",
			"roomFtmj": "15.23",
			"dj": "2171.99"
		},
		{
			"roomFh": "'2-504'",
			"roomSzc": "5",
			"roomSzdy": "'2'",
			"roomHtbah": "'361026202200155'",
			"roomGpdj": "2520",
			"roomGpshdj": "0",
			"roomJzmj": "78.45",
			"roomTnjzmj": "66.97",
			"roomFtmj": "11.48",
			"dj": "2171.99"
		},
		{
			"roomFh": "'3-505'",
			"roomSzc": "5",
			"roomSzdy": "'3'",
			"roomHtbah": "'361026202200221'",
			"roomGpdj": "2520",
			"roomGpshdj": "0",
			"roomJzmj": "78.45",
			"roomTnjzmj": "66.97",
			"roomFtmj": "11.48",
			"dj": "2171.99"
		},
		{
			"roomFh": "'3-506'",
			"roomSzc": "5",
			"roomSzdy": "'3'",
			"roomHtbah": "'361026202200147'",
			"roomGpdj": "2520",
			"roomGpshdj": "0",
			"roomJzmj": "104.14",
			"roomTnjzmj": "88.91",
			"roomFtmj": "15.23",
			"dj": "2171.99"
		},
		{
			"roomFh": "'4-507'",
			"roomSzc": "5",
			"roomSzdy": "'4'",
			"roomHtbah": "'361026202200024'",
			"roomGpdj": "2520",
			"roomGpshdj": "0",
			"roomJzmj": "91.11",
			"roomTnjzmj": "77.78",
			"roomFtmj": "13.33",
			"dj": "1321.21"
		},
		{
			"roomFh": "'4-508'",
			"roomSzc": "5",
			"roomSzdy": "'4'",
			"roomHtbah": "'361026202200112'",
			"roomGpdj": "2520",
			"roomGpshdj": "0",
			"roomJzmj": "108.15",
			"roomTnjzmj": "92.33",
			"roomFtmj": "15.82",
			"dj": "2171.99"
		}
	],
	"24栋": [
		{
			"roomFh": "'1-101'",
			"roomSzc": "1",
			"roomGpdj": "5000",
			"roomGpshdj": "0",
			"roomJzmj": "21.09",
			"roomTnjzmj": "20.46",
			"roomFtmj": "0.63",
			"dj": "0"
		},
		{
			"roomFh": "'1-102'",
			"roomSzc": "1",
			"roomHtbah": "'361026202200128'",
			"roomGpdj": "5000",
			"roomGpshdj": "0",
			"roomJzmj": "24.28",
			"roomTnjzmj": "23.56",
			"roomFtmj": "0.72",
			"dj": "1683.69"
		},
		{
			"roomFh": "'1-103'",
			"roomSzc": "1",
			"roomHtbah": "'361026202200127'",
			"roomGpdj": "5000",
			"roomGpshdj": "0",
			"roomJzmj": "16.61",
			"roomTnjzmj": "16.12",
			"roomFtmj": "0.49",
			"dj": "1683.68"
		},
		{
			"roomFh": "'1-104'",
			"roomSzc": "1",
			"roomHtbah": "'361026202300268'",
			"roomGpdj": "5000",
			"roomGpshdj": "0",
			"roomJzmj": "24.28",
			"roomTnjzmj": "23.56",
			"roomFtmj": "0.72",
			"dj": "2171.75"
		},
		{
			"roomFh": "'1-105'",
			"roomSzc": "1",
			"roomHtbah": "'361026202200120'",
			"roomGpdj": "5000",
			"roomGpshdj": "0",
			"roomJzmj": "22.37",
			"roomTnjzmj": "21.7",
			"roomFtmj": "0.67",
			"dj": "1683.68"
		},
		{
			"roomFh": "'1-121'",
			"roomSzc": "1",
			"roomGpdj": "5000",
			"roomGpshdj": "0",
			"roomJzmj": "15.99",
			"roomTnjzmj": "15.51",
			"roomFtmj": "0.48",
			"dj": "0"
		},
		{
			"roomFh": "'1-122'",
			"roomSzc": "1",
			"roomGpdj": "5000",
			"roomGpshdj": "0",
			"roomJzmj": "18.41",
			"roomTnjzmj": "17.86",
			"roomFtmj": "0.55",
			"dj": "0"
		},
		{
			"roomFh": "'1-123'",
			"roomSzc": "1",
			"roomGpdj": "5000",
			"roomGpshdj": "0",
			"roomJzmj": "15.02",
			"roomTnjzmj": "14.57",
			"roomFtmj": "0.45",
			"dj": "0"
		},
		{
			"roomFh": "'1-124'",
			"roomSzc": "1",
			"roomGpdj": "5000",
			"roomGpshdj": "0",
			"roomJzmj": "17.21",
			"roomTnjzmj": "16.7",
			"roomFtmj": "0.51",
			"dj": "0"
		},
		{
			"roomFh": "'2-106'",
			"roomSzc": "1",
			"roomHtbah": "'361026202300267'",
			"roomGpdj": "5000",
			"roomGpshdj": "0",
			"roomJzmj": "21.73",
			"roomTnjzmj": "21.08",
			"roomFtmj": "0.65",
			"dj": "2171.74"
		},
		{
			"roomFh": "'2-107'",
			"roomSzc": "1",
			"roomGpdj": "5000",
			"roomGpshdj": "0",
			"roomJzmj": "24.28",
			"roomTnjzmj": "23.56",
			"roomFtmj": "0.72",
			"dj": "0"
		},
		{
			"roomFh": "'2-108'",
			"roomSzc": "1",
			"roomHtbah": "'361026202200119'",
			"roomGpdj": "5000",
			"roomGpshdj": "0",
			"roomJzmj": "16.61",
			"roomTnjzmj": "16.12",
			"roomFtmj": "0.49",
			"dj": "1683.68"
		},
		{
			"roomFh": "'2-109'",
			"roomSzc": "1",
			"roomGpdj": "5000",
			"roomGpshdj": "0",
			"roomJzmj": "20.45",
			"roomTnjzmj": "19.84",
			"roomFtmj": "0.61",
			"dj": "0"
		},
		{
			"roomFh": "'2-110'",
			"roomSzc": "1",
			"roomGpdj": "5000",
			"roomGpshdj": "0",
			"roomJzmj": "19.81",
			"roomTnjzmj": "19.22",
			"roomFtmj": "0.59",
			"dj": "0"
		},
		{
			"roomFh": "'2-125'",
			"roomSzc": "1",
			"roomGpdj": "5000",
			"roomGpshdj": "0",
			"roomJzmj": "16.73",
			"roomTnjzmj": "16.23",
			"roomFtmj": "0.5",
			"dj": "0"
		},
		{
			"roomFh": "'2-126'",
			"roomSzc": "1",
			"roomGpdj": "5000",
			"roomGpshdj": "0",
			"roomJzmj": "15.02",
			"roomTnjzmj": "14.57",
			"roomFtmj": "0.45",
			"dj": "0"
		},
		{
			"roomFh": "'2-127'",
			"roomSzc": "1",
			"roomGpdj": "5000",
			"roomGpshdj": "0",
			"roomJzmj": "12.11",
			"roomTnjzmj": "11.75",
			"roomFtmj": "0.36",
			"dj": "0"
		},
		{
			"roomFh": "'2-128'",
			"roomSzc": "1",
			"roomGpdj": "5000",
			"roomGpshdj": "0",
			"roomJzmj": "15.27",
			"roomTnjzmj": "14.82",
			"roomFtmj": "0.45",
			"dj": "0"
		},
		{
			"roomFh": "'3-111'",
			"roomSzc": "1",
			"roomGpdj": "5000",
			"roomGpshdj": "0",
			"roomJzmj": "19.81",
			"roomTnjzmj": "19.22",
			"roomFtmj": "0.59",
			"dj": "0"
		},
		{
			"roomFh": "'3-112'",
			"roomSzc": "1",
			"roomGpdj": "5000",
			"roomGpshdj": "0",
			"roomJzmj": "20.45",
			"roomTnjzmj": "19.84",
			"roomFtmj": "0.61",
			"dj": "0"
		},
		{
			"roomFh": "'3-113'",
			"roomSzc": "1",
			"roomGpdj": "5000",
			"roomGpshdj": "0",
			"roomJzmj": "16.61",
			"roomTnjzmj": "16.12",
			"roomFtmj": "0.49",
			"dj": "0"
		},
		{
			"roomFh": "'3-114'",
			"roomSzc": "1",
			"roomGpdj": "5000",
			"roomGpshdj": "0",
			"roomJzmj": "24.28",
			"roomTnjzmj": "23.56",
			"roomFtmj": "0.72",
			"dj": "0"
		},
		{
			"roomFh": "'3-115'",
			"roomSzc": "1",
			"roomGpdj": "5000",
			"roomGpshdj": "0",
			"roomJzmj": "21.73",
			"roomTnjzmj": "21.08",
			"roomFtmj": "0.65",
			"dj": "0"
		},
		{
			"roomFh": "'3-129'",
			"roomSzc": "1",
			"roomGpdj": "5000",
			"roomGpshdj": "0",
			"roomJzmj": "15.27",
			"roomTnjzmj": "14.82",
			"roomFtmj": "0.45",
			"dj": "0"
		},
		{
			"roomFh": "'3-130'",
			"roomSzc": "1",
			"roomGpdj": "5000",
			"roomGpshdj": "0",
			"roomJzmj": "12.11",
			"roomTnjzmj": "11.75",
			"roomFtmj": "0.36",
			"dj": "0"
		},
		{
			"roomFh": "'3-131'",
			"roomSzc": "1",
			"roomGpdj": "5000",
			"roomGpshdj": "0",
			"roomJzmj": "15.02",
			"roomTnjzmj": "14.57",
			"roomFtmj": "0.45",
			"dj": "0"
		},
		{
			"roomFh": "'3-132'",
			"roomSzc": "1",
			"roomGpdj": "5000",
			"roomGpshdj": "0",
			"roomJzmj": "16.73",
			"roomTnjzmj": "16.23",
			"roomFtmj": "0.5",
			"dj": "0"
		},
		{
			"roomFh": "'4-116'",
			"roomSzc": "1",
			"roomGpdj": "5000",
			"roomGpshdj": "0",
			"roomJzmj": "22.37",
			"roomTnjzmj": "21.7",
			"roomFtmj": "0.67",
			"dj": "0"
		},
		{
			"roomFh": "'4-117'",
			"roomSzc": "1",
			"roomGpdj": "5000",
			"roomGpshdj": "0",
			"roomJzmj": "24.28",
			"roomTnjzmj": "23.56",
			"roomFtmj": "0.72",
			"dj": "0"
		},
		{
			"roomFh": "'4-118'",
			"roomSzc": "1",
			"roomGpdj": "5000",
			"roomGpshdj": "0",
			"roomJzmj": "16.61",
			"roomTnjzmj": "16.12",
			"roomFtmj": "0.49",
			"dj": "0"
		},
		{
			"roomFh": "'4-119'",
			"roomSzc": "1",
			"roomGpdj": "5000",
			"roomGpshdj": "0",
			"roomJzmj": "24.28",
			"roomTnjzmj": "23.56",
			"roomFtmj": "0.72",
			"dj": "0"
		},
		{
			"roomFh": "'4-120'",
			"roomSzc": "1",
			"roomGpdj": "5000",
			"roomGpshdj": "0",
			"roomJzmj": "21.09",
			"roomTnjzmj": "20.46",
			"roomFtmj": "0.63",
			"dj": "0"
		},
		{
			"roomFh": "'4-133'",
			"roomSzc": "1",
			"roomGpdj": "5000",
			"roomGpshdj": "0",
			"roomJzmj": "17.21",
			"roomTnjzmj": "16.7",
			"roomFtmj": "0.51",
			"dj": "0"
		},
		{
			"roomFh": "'4-134'",
			"roomSzc": "1",
			"roomGpdj": "5000",
			"roomGpshdj": "0",
			"roomJzmj": "15.02",
			"roomTnjzmj": "14.57",
			"roomFtmj": "0.45",
			"dj": "0"
		},
		{
			"roomFh": "'4-135'",
			"roomSzc": "1",
			"roomGpdj": "5000",
			"roomGpshdj": "0",
			"roomJzmj": "18.41",
			"roomTnjzmj": "17.86",
			"roomFtmj": "0.55",
			"dj": "0"
		},
		{
			"roomFh": "'4-136'",
			"roomSzc": "1",
			"roomGpdj": "5000",
			"roomGpshdj": "0",
			"roomJzmj": "15.99",
			"roomTnjzmj": "15.51",
			"roomFtmj": "0.48",
			"dj": "0"
		},
		{
			"roomFh": "'1-201'",
			"roomSzc": "2",
			"roomSzdy": "'1'",
			"roomHtbah": "'361026202200041'",
			"roomGpdj": "2520",
			"roomGpshdj": "0",
			"roomJzmj": "108.15",
			"roomTnjzmj": "92.33",
			"roomFtmj": "15.82",
			"dj": "1321.2"
		},
		{
			"roomFh": "'1-202'",
			"roomSzc": "2",
			"roomSzdy": "'1'",
			"roomHtbah": "'361026202200182'",
			"roomGpdj": "2520",
			"roomGpshdj": "0",
			"roomJzmj": "91.11",
			"roomTnjzmj": "77.78",
			"roomFtmj": "13.33",
			"dj": "2171.99"
		},
		{
			"roomFh": "'2-203'",
			"roomSzc": "2",
			"roomSzdy": "'2'",
			"roomHtbah": "'361026202200178'",
			"roomGpdj": "2520",
			"roomGpshdj": "0",
			"roomJzmj": "104.14",
			"roomTnjzmj": "88.91",
			"roomFtmj": "15.23",
			"dj": "2171.99"
		},
		{
			"roomFh": "'2-204'",
			"roomSzc": "2",
			"roomSzdy": "'2'",
			"roomHtbah": "'361026202200165'",
			"roomGpdj": "2520",
			"roomGpshdj": "0",
			"roomJzmj": "78.45",
			"roomTnjzmj": "66.97",
			"roomFtmj": "11.48",
			"dj": "2171.99"
		},
		{
			"roomFh": "'3-205'",
			"roomSzc": "2",
			"roomSzdy": "'3'",
			"roomHtbah": "'361026202200154'",
			"roomGpdj": "2520",
			"roomGpshdj": "0",
			"roomJzmj": "78.45",
			"roomTnjzmj": "66.97",
			"roomFtmj": "11.48",
			"dj": "2171.99"
		},
		{
			"roomFh": "'3-206'",
			"roomSzc": "2",
			"roomSzdy": "'3'",
			"roomHtbah": "'361026202200037'",
			"roomGpdj": "2520",
			"roomGpshdj": "0",
			"roomJzmj": "104.14",
			"roomTnjzmj": "88.91",
			"roomFtmj": "15.23",
			"dj": "1321.2"
		},
		{
			"roomFh": "'4-207'",
			"roomSzc": "2",
			"roomSzdy": "'4'",
			"roomHtbah": "'361026202200033'",
			"roomGpdj": "2520",
			"roomGpshdj": "0",
			"roomJzmj": "91.11",
			"roomTnjzmj": "77.78",
			"roomFtmj": "13.33",
			"dj": "1321.21"
		},
		{
			"roomFh": "'4-208'",
			"roomSzc": "2",
			"roomSzdy": "'4'",
			"roomHtbah": "'361026202200029'",
			"roomGpdj": "2520",
			"roomGpshdj": "0",
			"roomJzmj": "108.15",
			"roomTnjzmj": "92.33",
			"roomFtmj": "15.82",
			"dj": "1321.2"
		},
		{
			"roomFh": "'1-301'",
			"roomSzc": "3",
			"roomSzdy": "'1'",
			"roomHtbah": "'361026202200045'",
			"roomGpdj": "2680",
			"roomGpshdj": "0",
			"roomJzmj": "108.15",
			"roomTnjzmj": "92.33",
			"roomFtmj": "15.82",
			"dj": "1321.2"
		},
		{
			"roomFh": "'1-302'",
			"roomSzc": "3",
			"roomSzdy": "'1'",
			"roomHtbah": "'361026202200181'",
			"roomGpdj": "2680",
			"roomGpshdj": "0",
			"roomJzmj": "91.11",
			"roomTnjzmj": "77.78",
			"roomFtmj": "13.33",
			"dj": "2171.99"
		},
		{
			"roomFh": "'2-303'",
			"roomSzc": "3",
			"roomSzdy": "'2'",
			"roomHtbah": "'361026202200169'",
			"roomGpdj": "2680",
			"roomGpshdj": "0",
			"roomJzmj": "104.14",
			"roomTnjzmj": "88.91",
			"roomFtmj": "15.23",
			"dj": "2171.99"
		},
		{
			"roomFh": "'2-304'",
			"roomSzc": "3",
			"roomSzdy": "'2'",
			"roomHtbah": "'361026202200164'",
			"roomGpdj": "2680",
			"roomGpshdj": "0",
			"roomJzmj": "78.45",
			"roomTnjzmj": "66.97",
			"roomFtmj": "11.48",
			"dj": "2171.99"
		},
		{
			"roomFh": "'3-305'",
			"roomSzc": "3",
			"roomSzdy": "'3'",
			"roomHtbah": "'361026202200173'",
			"roomGpdj": "2680",
			"roomGpshdj": "0",
			"roomJzmj": "78.45",
			"roomTnjzmj": "66.97",
			"roomFtmj": "11.48",
			"dj": "2171.99"
		},
		{
			"roomFh": "'3-306'",
			"roomSzc": "3",
			"roomSzdy": "'3'",
			"roomHtbah": "'361026202200038'",
			"roomGpdj": "2680",
			"roomGpshdj": "0",
			"roomJzmj": "104.14",
			"roomTnjzmj": "88.91",
			"roomFtmj": "15.23",
			"dj": "1321.2"
		},
		{
			"roomFh": "'4-307'",
			"roomSzc": "3",
			"roomSzdy": "'4'",
			"roomHtbah": "'361026202200034'",
			"roomGpdj": "2680",
			"roomGpshdj": "0",
			"roomJzmj": "91.11",
			"roomTnjzmj": "77.78",
			"roomFtmj": "13.33",
			"dj": "1321.21"
		},
		{
			"roomFh": "'4-308'",
			"roomSzc": "3",
			"roomSzdy": "'4'",
			"roomHtbah": "'361026202200030'",
			"roomGpdj": "2680",
			"roomGpshdj": "0",
			"roomJzmj": "108.15",
			"roomTnjzmj": "92.33",
			"roomFtmj": "15.82",
			"dj": "1321.2"
		},
		{
			"roomFh": "'1-401'",
			"roomSzc": "4",
			"roomSzdy": "'1'",
			"roomHtbah": "'361026202200042'",
			"roomGpdj": "2680",
			"roomGpshdj": "0",
			"roomJzmj": "108.15",
			"roomTnjzmj": "92.33",
			"roomFtmj": "15.82",
			"dj": "1321.2"
		},
		{
			"roomFh": "'1-402'",
			"roomSzc": "4",
			"roomSzdy": "'1'",
			"roomHtbah": "'361026202200180'",
			"roomGpdj": "2680",
			"roomGpshdj": "0",
			"roomJzmj": "91.11",
			"roomTnjzmj": "77.78",
			"roomFtmj": "13.33",
			"dj": "2171.99"
		},
		{
			"roomFh": "'2-403'",
			"roomSzc": "4",
			"roomSzdy": "'2'",
			"roomHtbah": "'361026202200167'",
			"roomGpdj": "2680",
			"roomGpshdj": "0",
			"roomJzmj": "104.14",
			"roomTnjzmj": "88.91",
			"roomFtmj": "15.23",
			"dj": "2171.99"
		},
		{
			"roomFh": "'2-404'",
			"roomSzc": "4",
			"roomSzdy": "'2'",
			"roomHtbah": "'361026202200156'",
			"roomGpdj": "2680",
			"roomGpshdj": "0",
			"roomJzmj": "78.45",
			"roomTnjzmj": "66.97",
			"roomFtmj": "11.48",
			"dj": "2171.99"
		},
		{
			"roomFh": "'3-405'",
			"roomSzc": "4",
			"roomSzdy": "'3'",
			"roomHtbah": "'361026202200172'",
			"roomGpdj": "2680",
			"roomGpshdj": "0",
			"roomJzmj": "78.45",
			"roomTnjzmj": "66.97",
			"roomFtmj": "11.48",
			"dj": "2171.99"
		},
		{
			"roomFh": "'3-406'",
			"roomSzc": "4",
			"roomSzdy": "'3'",
			"roomHtbah": "'361026202200039'",
			"roomGpdj": "2680",
			"roomGpshdj": "0",
			"roomJzmj": "104.14",
			"roomTnjzmj": "88.91",
			"roomFtmj": "15.23",
			"dj": "1321.2"
		},
		{
			"roomFh": "'4-407'",
			"roomSzc": "4",
			"roomSzdy": "'4'",
			"roomHtbah": "'361026202200035'",
			"roomGpdj": "2680",
			"roomGpshdj": "0",
			"roomJzmj": "91.11",
			"roomTnjzmj": "77.78",
			"roomFtmj": "13.33",
			"dj": "1321.21"
		},
		{
			"roomFh": "'4-408'",
			"roomSzc": "4",
			"roomSzdy": "'4'",
			"roomHtbah": "'361026202200031'",
			"roomGpdj": "2680",
			"roomGpshdj": "0",
			"roomJzmj": "108.15",
			"roomTnjzmj": "92.33",
			"roomFtmj": "15.82",
			"dj": "1321.2"
		},
		{
			"roomFh": "'1-501'",
			"roomSzc": "5",
			"roomSzdy": "'1'",
			"roomHtbah": "'361026202200043'",
			"roomGpdj": "2520",
			"roomGpshdj": "0",
			"roomJzmj": "108.15",
			"roomTnjzmj": "92.33",
			"roomFtmj": "15.82",
			"dj": "1321.2"
		},
		{
			"roomFh": "'1-502'",
			"roomSzc": "5",
			"roomSzdy": "'1'",
			"roomHtbah": "'361026202200171'",
			"roomGpdj": "2520",
			"roomGpshdj": "0",
			"roomJzmj": "91.11",
			"roomTnjzmj": "77.78",
			"roomFtmj": "13.33",
			"dj": "2171.99"
		},
		{
			"roomFh": "'2-503'",
			"roomSzc": "5",
			"roomSzdy": "'2'",
			"roomHtbah": "'361026202200230'",
			"roomGpdj": "2520",
			"roomGpshdj": "0",
			"roomJzmj": "104.14",
			"roomTnjzmj": "88.91",
			"roomFtmj": "15.23",
			"dj": "2171.99"
		},
		{
			"roomFh": "'2-504'",
			"roomSzc": "5",
			"roomSzdy": "'2'",
			"roomHtbah": "'361026202200176'",
			"roomGpdj": "2520",
			"roomGpshdj": "0",
			"roomJzmj": "78.45",
			"roomTnjzmj": "66.97",
			"roomFtmj": "11.48",
			"dj": "2171.99"
		},
		{
			"roomFh": "'3-505'",
			"roomSzc": "5",
			"roomSzdy": "'3'",
			"roomHtbah": "'361026202200158'",
			"roomGpdj": "2520",
			"roomGpshdj": "0",
			"roomJzmj": "78.45",
			"roomTnjzmj": "66.97",
			"roomFtmj": "11.48",
			"dj": "2171.99"
		},
		{
			"roomFh": "'3-506'",
			"roomSzc": "5",
			"roomSzdy": "'3'",
			"roomHtbah": "'361026202200040'",
			"roomGpdj": "2520",
			"roomGpshdj": "0",
			"roomJzmj": "104.14",
			"roomTnjzmj": "88.91",
			"roomFtmj": "15.23",
			"dj": "1321.2"
		},
		{
			"roomFh": "'4-507'",
			"roomSzc": "5",
			"roomSzdy": "'4'",
			"roomHtbah": "'361026202200036'",
			"roomGpdj": "2520",
			"roomGpshdj": "0",
			"roomJzmj": "91.11",
			"roomTnjzmj": "77.78",
			"roomFtmj": "13.33",
			"dj": "1321.21"
		},
		{
			"roomFh": "'4-508'",
			"roomSzc": "5",
			"roomSzdy": "'4'",
			"roomHtbah": "'361026202200032'",
			"roomGpdj": "2520",
			"roomGpshdj": "0",
			"roomJzmj": "108.15",
			"roomTnjzmj": "92.33",
			"roomFtmj": "15.82",
			"dj": "1321.2"
		}
	],
	"25栋": [
		{
			"roomFh": "'1-101'",
			"roomSzc": "1",
			"roomGpdj": "5000",
			"roomGpshdj": "0",
			"roomJzmj": "21.09",
			"roomTnjzmj": "20.46",
			"roomFtmj": "0.63",
			"dj": "0"
		},
		{
			"roomFh": "'1-102'",
			"roomSzc": "1",
			"roomGpdj": "5000",
			"roomGpshdj": "0",
			"roomJzmj": "24.28",
			"roomTnjzmj": "23.56",
			"roomFtmj": "0.72",
			"dj": "0"
		},
		{
			"roomFh": "'1-103'",
			"roomSzc": "1",
			"roomGpdj": "5000",
			"roomGpshdj": "0",
			"roomJzmj": "16.61",
			"roomTnjzmj": "16.12",
			"roomFtmj": "0.49",
			"dj": "0"
		},
		{
			"roomFh": "'1-104'",
			"roomSzc": "1",
			"roomGpdj": "5000",
			"roomGpshdj": "0",
			"roomJzmj": "24.28",
			"roomTnjzmj": "23.56",
			"roomFtmj": "0.72",
			"dj": "0"
		},
		{
			"roomFh": "'1-105'",
			"roomSzc": "1",
			"roomGpdj": "5000",
			"roomGpshdj": "0",
			"roomJzmj": "22.37",
			"roomTnjzmj": "21.7",
			"roomFtmj": "0.67",
			"dj": "0"
		},
		{
			"roomFh": "'1-121'",
			"roomSzc": "1",
			"roomGpdj": "5000",
			"roomGpshdj": "0",
			"roomJzmj": "15.99",
			"roomTnjzmj": "15.51",
			"roomFtmj": "0.48",
			"dj": "0"
		},
		{
			"roomFh": "'1-122'",
			"roomSzc": "1",
			"roomGpdj": "5000",
			"roomGpshdj": "0",
			"roomJzmj": "18.41",
			"roomTnjzmj": "17.86",
			"roomFtmj": "0.55",
			"dj": "0"
		},
		{
			"roomFh": "'1-123'",
			"roomSzc": "1",
			"roomGpdj": "5000",
			"roomGpshdj": "0",
			"roomJzmj": "15.02",
			"roomTnjzmj": "14.57",
			"roomFtmj": "0.45",
			"dj": "0"
		},
		{
			"roomFh": "'1-124'",
			"roomSzc": "1",
			"roomGpdj": "5000",
			"roomGpshdj": "0",
			"roomJzmj": "17.21",
			"roomTnjzmj": "16.7",
			"roomFtmj": "0.51",
			"dj": "0"
		},
		{
			"roomFh": "'2-106'",
			"roomSzc": "1",
			"roomGpdj": "5000",
			"roomGpshdj": "0",
			"roomJzmj": "21.73",
			"roomTnjzmj": "21.08",
			"roomFtmj": "0.65",
			"dj": "0"
		},
		{
			"roomFh": "'2-107'",
			"roomSzc": "1",
			"roomGpdj": "5000",
			"roomGpshdj": "0",
			"roomJzmj": "24.28",
			"roomTnjzmj": "23.56",
			"roomFtmj": "0.72",
			"dj": "0"
		},
		{
			"roomFh": "'2-108'",
			"roomSzc": "1",
			"roomGpdj": "5000",
			"roomGpshdj": "0",
			"roomJzmj": "16.61",
			"roomTnjzmj": "16.12",
			"roomFtmj": "0.49",
			"dj": "0"
		},
		{
			"roomFh": "'2-109'",
			"roomSzc": "1",
			"roomGpdj": "5000",
			"roomGpshdj": "0",
			"roomJzmj": "20.45",
			"roomTnjzmj": "19.84",
			"roomFtmj": "0.61",
			"dj": "0"
		},
		{
			"roomFh": "'2-110'",
			"roomSzc": "1",
			"roomGpdj": "5000",
			"roomGpshdj": "0",
			"roomJzmj": "19.81",
			"roomTnjzmj": "19.22",
			"roomFtmj": "0.59",
			"dj": "0"
		},
		{
			"roomFh": "'2-125'",
			"roomSzc": "1",
			"roomGpdj": "5000",
			"roomGpshdj": "0",
			"roomJzmj": "16.73",
			"roomTnjzmj": "16.23",
			"roomFtmj": "0.5",
			"dj": "0"
		},
		{
			"roomFh": "'2-126'",
			"roomSzc": "1",
			"roomGpdj": "5000",
			"roomGpshdj": "0",
			"roomJzmj": "15.02",
			"roomTnjzmj": "14.57",
			"roomFtmj": "0.45",
			"dj": "0"
		},
		{
			"roomFh": "'2-127'",
			"roomSzc": "1",
			"roomGpdj": "5000",
			"roomGpshdj": "0",
			"roomJzmj": "12.11",
			"roomTnjzmj": "11.75",
			"roomFtmj": "0.36",
			"dj": "0"
		},
		{
			"roomFh": "'2-128'",
			"roomSzc": "1",
			"roomGpdj": "5000",
			"roomGpshdj": "0",
			"roomJzmj": "15.27",
			"roomTnjzmj": "14.82",
			"roomFtmj": "0.45",
			"dj": "0"
		},
		{
			"roomFh": "'3-111'",
			"roomSzc": "1",
			"roomGpdj": "5000",
			"roomGpshdj": "0",
			"roomJzmj": "19.81",
			"roomTnjzmj": "19.22",
			"roomFtmj": "0.59",
			"dj": "0"
		},
		{
			"roomFh": "'3-112'",
			"roomSzc": "1",
			"roomGpdj": "5000",
			"roomGpshdj": "0",
			"roomJzmj": "20.45",
			"roomTnjzmj": "19.84",
			"roomFtmj": "0.61",
			"dj": "0"
		},
		{
			"roomFh": "'3-113'",
			"roomSzc": "1",
			"roomGpdj": "5000",
			"roomGpshdj": "0",
			"roomJzmj": "16.61",
			"roomTnjzmj": "16.12",
			"roomFtmj": "0.49",
			"dj": "0"
		},
		{
			"roomFh": "'3-114'",
			"roomSzc": "1",
			"roomGpdj": "5000",
			"roomGpshdj": "0",
			"roomJzmj": "24.28",
			"roomTnjzmj": "23.56",
			"roomFtmj": "0.72",
			"dj": "0"
		},
		{
			"roomFh": "'3-115'",
			"roomSzc": "1",
			"roomGpdj": "5000",
			"roomGpshdj": "0",
			"roomJzmj": "21.73",
			"roomTnjzmj": "21.08",
			"roomFtmj": "0.65",
			"dj": "0"
		},
		{
			"roomFh": "'3-129'",
			"roomSzc": "1",
			"roomGpdj": "5000",
			"roomGpshdj": "0",
			"roomJzmj": "15.27",
			"roomTnjzmj": "14.82",
			"roomFtmj": "0.45",
			"dj": "0"
		},
		{
			"roomFh": "'3-130'",
			"roomSzc": "1",
			"roomGpdj": "5000",
			"roomGpshdj": "0",
			"roomJzmj": "12.11",
			"roomTnjzmj": "11.75",
			"roomFtmj": "0.36",
			"dj": "0"
		},
		{
			"roomFh": "'3-131'",
			"roomSzc": "1",
			"roomGpdj": "5000",
			"roomGpshdj": "0",
			"roomJzmj": "15.02",
			"roomTnjzmj": "14.57",
			"roomFtmj": "0.45",
			"dj": "0"
		},
		{
			"roomFh": "'3-132'",
			"roomSzc": "1",
			"roomGpdj": "5000",
			"roomGpshdj": "0",
			"roomJzmj": "16.73",
			"roomTnjzmj": "16.23",
			"roomFtmj": "0.5",
			"dj": "0"
		},
		{
			"roomFh": "'4-116'",
			"roomSzc": "1",
			"roomGpdj": "5000",
			"roomGpshdj": "0",
			"roomJzmj": "22.37",
			"roomTnjzmj": "21.7",
			"roomFtmj": "0.67",
			"dj": "0"
		},
		{
			"roomFh": "'4-117'",
			"roomSzc": "1",
			"roomGpdj": "5000",
			"roomGpshdj": "0",
			"roomJzmj": "24.28",
			"roomTnjzmj": "23.56",
			"roomFtmj": "0.72",
			"dj": "0"
		},
		{
			"roomFh": "'4-118'",
			"roomSzc": "1",
			"roomGpdj": "5000",
			"roomGpshdj": "0",
			"roomJzmj": "16.61",
			"roomTnjzmj": "16.12",
			"roomFtmj": "0.49",
			"dj": "0"
		},
		{
			"roomFh": "'4-119'",
			"roomSzc": "1",
			"roomGpdj": "5000",
			"roomGpshdj": "0",
			"roomJzmj": "24.28",
			"roomTnjzmj": "23.56",
			"roomFtmj": "0.72",
			"dj": "0"
		},
		{
			"roomFh": "'4-120'",
			"roomSzc": "1",
			"roomGpdj": "5000",
			"roomGpshdj": "0",
			"roomJzmj": "21.09",
			"roomTnjzmj": "20.46",
			"roomFtmj": "0.63",
			"dj": "0"
		},
		{
			"roomFh": "'4-133'",
			"roomSzc": "1",
			"roomGpdj": "5000",
			"roomGpshdj": "0",
			"roomJzmj": "17.21",
			"roomTnjzmj": "16.7",
			"roomFtmj": "0.51",
			"dj": "0"
		},
		{
			"roomFh": "'4-134'",
			"roomSzc": "1",
			"roomGpdj": "5000",
			"roomGpshdj": "0",
			"roomJzmj": "15.02",
			"roomTnjzmj": "14.57",
			"roomFtmj": "0.45",
			"dj": "0"
		},
		{
			"roomFh": "'4-135'",
			"roomSzc": "1",
			"roomGpdj": "5000",
			"roomGpshdj": "0",
			"roomJzmj": "18.41",
			"roomTnjzmj": "17.86",
			"roomFtmj": "0.55",
			"dj": "0"
		},
		{
			"roomFh": "'4-136'",
			"roomSzc": "1",
			"roomGpdj": "5000",
			"roomGpshdj": "0",
			"roomJzmj": "15.99",
			"roomTnjzmj": "15.51",
			"roomFtmj": "0.48",
			"dj": "0"
		},
		{
			"roomFh": "'1-201'",
			"roomSzc": "2",
			"roomSzdy": "'1'",
			"roomGpdj": "2520",
			"roomGpshdj": "0",
			"roomJzmj": "108.15",
			"roomTnjzmj": "92.33",
			"roomFtmj": "15.82",
			"dj": "0"
		},
		{
			"roomFh": "'1-202'",
			"roomSzc": "2",
			"roomSzdy": "'1'",
			"roomHtbah": "'361026202200051'",
			"roomGpdj": "2520",
			"roomGpshdj": "0",
			"roomJzmj": "91.11",
			"roomTnjzmj": "77.78",
			"roomFtmj": "13.33",
			"dj": "1321.21"
		},
		{
			"roomFh": "'2-203'",
			"roomSzc": "2",
			"roomSzdy": "'2'",
			"roomGpdj": "2520",
			"roomGpshdj": "0",
			"roomJzmj": "104.14",
			"roomTnjzmj": "88.91",
			"roomFtmj": "15.23",
			"dj": "0"
		},
		{
			"roomFh": "'2-204'",
			"roomSzc": "2",
			"roomSzdy": "'2'",
			"roomHtbah": "'361026202200179'",
			"roomGpdj": "2520",
			"roomGpshdj": "0",
			"roomJzmj": "78.45",
			"roomTnjzmj": "66.97",
			"roomFtmj": "11.48",
			"dj": "2171.99"
		},
		{
			"roomFh": "'3-205'",
			"roomSzc": "2",
			"roomSzdy": "'3'",
			"roomGpdj": "2520",
			"roomGpshdj": "0",
			"roomJzmj": "78.45",
			"roomTnjzmj": "66.97",
			"roomFtmj": "11.48",
			"dj": "0"
		},
		{
			"roomFh": "'3-206'",
			"roomSzc": "2",
			"roomSzdy": "'3'",
			"roomGpdj": "2520",
			"roomGpshdj": "0",
			"roomJzmj": "104.14",
			"roomTnjzmj": "88.91",
			"roomFtmj": "15.23",
			"dj": "0"
		},
		{
			"roomFh": "'4-207'",
			"roomSzc": "2",
			"roomSzdy": "'4'",
			"roomGpdj": "2520",
			"roomGpshdj": "0",
			"roomJzmj": "91.11",
			"roomTnjzmj": "77.78",
			"roomFtmj": "13.33",
			"dj": "0"
		},
		{
			"roomFh": "'4-208'",
			"roomSzc": "2",
			"roomSzdy": "'4'",
			"roomGpdj": "2520",
			"roomGpshdj": "0",
			"roomJzmj": "108.15",
			"roomTnjzmj": "92.33",
			"roomFtmj": "15.82",
			"dj": "0"
		},
		{
			"roomFh": "'1-301'",
			"roomSzc": "3",
			"roomSzdy": "'1'",
			"roomGpdj": "2680",
			"roomGpshdj": "0",
			"roomJzmj": "108.15",
			"roomTnjzmj": "92.33",
			"roomFtmj": "15.82",
			"dj": "0"
		},
		{
			"roomFh": "'1-302'",
			"roomSzc": "3",
			"roomSzdy": "'1'",
			"roomHtbah": "'361026202200053'",
			"roomGpdj": "2680",
			"roomGpshdj": "0",
			"roomJzmj": "91.11",
			"roomTnjzmj": "77.78",
			"roomFtmj": "13.33",
			"dj": "1321.21"
		},
		{
			"roomFh": "'2-303'",
			"roomSzc": "3",
			"roomSzdy": "'2'",
			"roomHtbah": "'361026202200231'",
			"roomGpdj": "2680",
			"roomGpshdj": "0",
			"roomJzmj": "104.14",
			"roomTnjzmj": "88.91",
			"roomFtmj": "15.23",
			"dj": "2171.99"
		},
		{
			"roomFh": "'2-304'",
			"roomSzc": "3",
			"roomSzdy": "'2'",
			"roomHtbah": "'361026202200177'",
			"roomGpdj": "2680",
			"roomGpshdj": "0",
			"roomJzmj": "78.45",
			"roomTnjzmj": "66.97",
			"roomFtmj": "11.48",
			"dj": "2171.99"
		},
		{
			"roomFh": "'3-305'",
			"roomSzc": "3",
			"roomSzdy": "'3'",
			"roomHtbah": "'361026202200188'",
			"roomGpdj": "2680",
			"roomGpshdj": "0",
			"roomJzmj": "78.45",
			"roomTnjzmj": "66.97",
			"roomFtmj": "11.48",
			"dj": "2171.99"
		},
		{
			"roomFh": "'3-306'",
			"roomSzc": "3",
			"roomSzdy": "'3'",
			"roomGpdj": "2680",
			"roomGpshdj": "0",
			"roomJzmj": "104.14",
			"roomTnjzmj": "88.91",
			"roomFtmj": "15.23",
			"dj": "0"
		},
		{
			"roomFh": "'4-307'",
			"roomSzc": "3",
			"roomSzdy": "'4'",
			"roomHtbah": "'361026202200046'",
			"roomGpdj": "2680",
			"roomGpshdj": "0",
			"roomJzmj": "91.11",
			"roomTnjzmj": "77.78",
			"roomFtmj": "13.33",
			"dj": "1321.21"
		},
		{
			"roomFh": "'4-308'",
			"roomSzc": "3",
			"roomSzdy": "'4'",
			"roomGpdj": "2680",
			"roomGpshdj": "0",
			"roomJzmj": "108.15",
			"roomTnjzmj": "92.33",
			"roomFtmj": "15.82",
			"dj": "0"
		},
		{
			"roomFh": "'1-401'",
			"roomSzc": "4",
			"roomSzdy": "'1'",
			"roomHtbah": "'361026202200055'",
			"roomGpdj": "2680",
			"roomGpshdj": "0",
			"roomJzmj": "108.15",
			"roomTnjzmj": "92.33",
			"roomFtmj": "15.82",
			"dj": "1321.2"
		},
		{
			"roomFh": "'1-402'",
			"roomSzc": "4",
			"roomSzdy": "'1'",
			"roomHtbah": "'361026202200052'",
			"roomGpdj": "2680",
			"roomGpshdj": "0",
			"roomJzmj": "91.11",
			"roomTnjzmj": "77.78",
			"roomFtmj": "13.33",
			"dj": "1321.21"
		},
		{
			"roomFh": "'2-403'",
			"roomSzc": "4",
			"roomSzdy": "'2'",
			"roomGpdj": "2680",
			"roomGpshdj": "0",
			"roomJzmj": "104.14",
			"roomTnjzmj": "88.91",
			"roomFtmj": "15.23",
			"dj": "0"
		},
		{
			"roomFh": "'2-404'",
			"roomSzc": "4",
			"roomSzdy": "'2'",
			"roomHtbah": "'361026202200175'",
			"roomGpdj": "2680",
			"roomGpshdj": "0",
			"roomJzmj": "78.45",
			"roomTnjzmj": "66.97",
			"roomFtmj": "11.48",
			"dj": "2171.99"
		},
		{
			"roomFh": "'3-405'",
			"roomSzc": "4",
			"roomSzdy": "'3'",
			"roomHtbah": "'361026202200174'",
			"roomGpdj": "2680",
			"roomGpshdj": "0",
			"roomJzmj": "78.45",
			"roomTnjzmj": "66.97",
			"roomFtmj": "11.48",
			"dj": "2171.99"
		},
		{
			"roomFh": "'3-406'",
			"roomSzc": "4",
			"roomSzdy": "'3'",
			"roomGpdj": "2680",
			"roomGpshdj": "0",
			"roomJzmj": "104.14",
			"roomTnjzmj": "88.91",
			"roomFtmj": "15.23",
			"dj": "0"
		},
		{
			"roomFh": "'4-407'",
			"roomSzc": "4",
			"roomSzdy": "'4'",
			"roomHtbah": "'361026202200047'",
			"roomGpdj": "2680",
			"roomGpshdj": "0",
			"roomJzmj": "91.11",
			"roomTnjzmj": "77.78",
			"roomFtmj": "13.33",
			"dj": "1321.21"
		},
		{
			"roomFh": "'4-408'",
			"roomSzc": "4",
			"roomSzdy": "'4'",
			"roomGpdj": "2680",
			"roomGpshdj": "0",
			"roomJzmj": "108.15",
			"roomTnjzmj": "92.33",
			"roomFtmj": "15.82",
			"dj": "0"
		},
		{
			"roomFh": "'1-501'",
			"roomSzc": "5",
			"roomSzdy": "'1'",
			"roomHtbah": "'361026202200056'",
			"roomGpdj": "2520",
			"roomGpshdj": "0",
			"roomJzmj": "108.15",
			"roomTnjzmj": "92.33",
			"roomFtmj": "15.82",
			"dj": "1321.2"
		},
		{
			"roomFh": "'1-502'",
			"roomSzc": "5",
			"roomSzdy": "'1'",
			"roomHtbah": "'361026202200054'",
			"roomGpdj": "2520",
			"roomGpshdj": "0",
			"roomJzmj": "91.11",
			"roomTnjzmj": "77.78",
			"roomFtmj": "13.33",
			"dj": "1321.21"
		},
		{
			"roomFh": "'2-503'",
			"roomSzc": "5",
			"roomSzdy": "'2'",
			"roomHtbah": "'361026202200050'",
			"roomGpdj": "2520",
			"roomGpshdj": "0",
			"roomJzmj": "104.14",
			"roomTnjzmj": "88.91",
			"roomFtmj": "15.23",
			"dj": "1321.2"
		},
		{
			"roomFh": "'2-504'",
			"roomSzc": "5",
			"roomSzdy": "'2'",
			"roomHtbah": "'361026202200189'",
			"roomGpdj": "2520",
			"roomGpshdj": "0",
			"roomJzmj": "78.45",
			"roomTnjzmj": "66.97",
			"roomFtmj": "11.48",
			"dj": "2171.99"
		},
		{
			"roomFh": "'3-505'",
			"roomSzc": "5",
			"roomSzdy": "'3'",
			"roomHtbah": "'361026202200185'",
			"roomGpdj": "2520",
			"roomGpshdj": "0",
			"roomJzmj": "78.45",
			"roomTnjzmj": "66.97",
			"roomFtmj": "11.48",
			"dj": "2171.99"
		},
		{
			"roomFh": "'3-506'",
			"roomSzc": "5",
			"roomSzdy": "'3'",
			"roomHtbah": "'361026202200049'",
			"roomGpdj": "2520",
			"roomGpshdj": "0",
			"roomJzmj": "104.14",
			"roomTnjzmj": "88.91",
			"roomFtmj": "15.23",
			"dj": "1321.2"
		},
		{
			"roomFh": "'4-507'",
			"roomSzc": "5",
			"roomSzdy": "'4'",
			"roomHtbah": "'361026202200048'",
			"roomGpdj": "2520",
			"roomGpshdj": "0",
			"roomJzmj": "91.11",
			"roomTnjzmj": "77.78",
			"roomFtmj": "13.33",
			"dj": "1321.21"
		},
		{
			"roomFh": "'4-508'",
			"roomSzc": "5",
			"roomSzdy": "'4'",
			"roomHtbah": "'361026202200044'",
			"roomGpdj": "2520",
			"roomGpshdj": "0",
			"roomJzmj": "108.15",
			"roomTnjzmj": "92.33",
			"roomFtmj": "15.82",
			"dj": "1321.2"
		}
	],
	"26栋": [
		{
			"roomFh": "'1-101'",
			"roomSzc": "1",
			"roomGpdj": "5000",
			"roomGpshdj": "0",
			"roomJzmj": "21.09",
			"roomTnjzmj": "20.46",
			"roomFtmj": "0.63",
			"dj": "0"
		},
		{
			"roomFh": "'1-102'",
			"roomSzc": "1",
			"roomGpdj": "5000",
			"roomGpshdj": "0",
			"roomJzmj": "24.28",
			"roomTnjzmj": "23.56",
			"roomFtmj": "0.72",
			"dj": "0"
		},
		{
			"roomFh": "'1-103'",
			"roomSzc": "1",
			"roomGpdj": "5000",
			"roomGpshdj": "0",
			"roomJzmj": "16.61",
			"roomTnjzmj": "16.12",
			"roomFtmj": "0.49",
			"dj": "0"
		},
		{
			"roomFh": "'1-104'",
			"roomSzc": "1",
			"roomGpdj": "5000",
			"roomGpshdj": "0",
			"roomJzmj": "24.28",
			"roomTnjzmj": "23.56",
			"roomFtmj": "0.72",
			"dj": "0"
		},
		{
			"roomFh": "'1-105'",
			"roomSzc": "1",
			"roomGpdj": "5000",
			"roomGpshdj": "0",
			"roomJzmj": "22.37",
			"roomTnjzmj": "21.7",
			"roomFtmj": "0.67",
			"dj": "0"
		},
		{
			"roomFh": "'1-121'",
			"roomSzc": "1",
			"roomGpdj": "5000",
			"roomGpshdj": "0",
			"roomJzmj": "15.99",
			"roomTnjzmj": "15.51",
			"roomFtmj": "0.48",
			"dj": "0"
		},
		{
			"roomFh": "'1-122'",
			"roomSzc": "1",
			"roomGpdj": "5000",
			"roomGpshdj": "0",
			"roomJzmj": "18.41",
			"roomTnjzmj": "17.86",
			"roomFtmj": "0.55",
			"dj": "0"
		},
		{
			"roomFh": "'1-123'",
			"roomSzc": "1",
			"roomGpdj": "5000",
			"roomGpshdj": "0",
			"roomJzmj": "15.02",
			"roomTnjzmj": "14.57",
			"roomFtmj": "0.45",
			"dj": "0"
		},
		{
			"roomFh": "'1-124'",
			"roomSzc": "1",
			"roomGpdj": "5000",
			"roomGpshdj": "0",
			"roomJzmj": "17.21",
			"roomTnjzmj": "16.7",
			"roomFtmj": "0.51",
			"dj": "0"
		},
		{
			"roomFh": "'2-106'",
			"roomSzc": "1",
			"roomGpdj": "5000",
			"roomGpshdj": "0",
			"roomJzmj": "21.73",
			"roomTnjzmj": "21.08",
			"roomFtmj": "0.65",
			"dj": "0"
		},
		{
			"roomFh": "'2-107'",
			"roomSzc": "1",
			"roomGpdj": "5000",
			"roomGpshdj": "0",
			"roomJzmj": "24.28",
			"roomTnjzmj": "23.56",
			"roomFtmj": "0.72",
			"dj": "0"
		},
		{
			"roomFh": "'2-108'",
			"roomSzc": "1",
			"roomGpdj": "5000",
			"roomGpshdj": "0",
			"roomJzmj": "16.61",
			"roomTnjzmj": "16.12",
			"roomFtmj": "0.49",
			"dj": "0"
		},
		{
			"roomFh": "'2-109'",
			"roomSzc": "1",
			"roomGpdj": "5000",
			"roomGpshdj": "0",
			"roomJzmj": "20.45",
			"roomTnjzmj": "19.84",
			"roomFtmj": "0.61",
			"dj": "0"
		},
		{
			"roomFh": "'2-110'",
			"roomSzc": "1",
			"roomGpdj": "5000",
			"roomGpshdj": "0",
			"roomJzmj": "19.81",
			"roomTnjzmj": "19.22",
			"roomFtmj": "0.59",
			"dj": "0"
		},
		{
			"roomFh": "'2-125'",
			"roomSzc": "1",
			"roomGpdj": "5000",
			"roomGpshdj": "0",
			"roomJzmj": "16.73",
			"roomTnjzmj": "16.23",
			"roomFtmj": "0.5",
			"dj": "0"
		},
		{
			"roomFh": "'2-126'",
			"roomSzc": "1",
			"roomGpdj": "5000",
			"roomGpshdj": "0",
			"roomJzmj": "15.02",
			"roomTnjzmj": "14.57",
			"roomFtmj": "0.45",
			"dj": "0"
		},
		{
			"roomFh": "'2-127'",
			"roomSzc": "1",
			"roomGpdj": "5000",
			"roomGpshdj": "0",
			"roomJzmj": "12.11",
			"roomTnjzmj": "11.75",
			"roomFtmj": "0.36",
			"dj": "0"
		},
		{
			"roomFh": "'2-128'",
			"roomSzc": "1",
			"roomGpdj": "5000",
			"roomGpshdj": "0",
			"roomJzmj": "15.27",
			"roomTnjzmj": "14.82",
			"roomFtmj": "0.45",
			"dj": "0"
		},
		{
			"roomFh": "'3-111'",
			"roomSzc": "1",
			"roomGpdj": "5000",
			"roomGpshdj": "0",
			"roomJzmj": "19.81",
			"roomTnjzmj": "19.22",
			"roomFtmj": "0.59",
			"dj": "0"
		},
		{
			"roomFh": "'3-112'",
			"roomSzc": "1",
			"roomGpdj": "5000",
			"roomGpshdj": "0",
			"roomJzmj": "20.45",
			"roomTnjzmj": "19.84",
			"roomFtmj": "0.61",
			"dj": "0"
		},
		{
			"roomFh": "'3-113'",
			"roomSzc": "1",
			"roomGpdj": "5000",
			"roomGpshdj": "0",
			"roomJzmj": "16.61",
			"roomTnjzmj": "16.12",
			"roomFtmj": "0.49",
			"dj": "0"
		},
		{
			"roomFh": "'3-114'",
			"roomSzc": "1",
			"roomGpdj": "5000",
			"roomGpshdj": "0",
			"roomJzmj": "24.28",
			"roomTnjzmj": "23.56",
			"roomFtmj": "0.72",
			"dj": "0"
		},
		{
			"roomFh": "'3-115'",
			"roomSzc": "1",
			"roomGpdj": "5000",
			"roomGpshdj": "0",
			"roomJzmj": "21.73",
			"roomTnjzmj": "21.08",
			"roomFtmj": "0.65",
			"dj": "0"
		},
		{
			"roomFh": "'3-129'",
			"roomSzc": "1",
			"roomGpdj": "5000",
			"roomGpshdj": "0",
			"roomJzmj": "15.27",
			"roomTnjzmj": "14.82",
			"roomFtmj": "0.45",
			"dj": "0"
		},
		{
			"roomFh": "'3-130'",
			"roomSzc": "1",
			"roomGpdj": "5000",
			"roomGpshdj": "0",
			"roomJzmj": "12.11",
			"roomTnjzmj": "11.75",
			"roomFtmj": "0.36",
			"dj": "0"
		},
		{
			"roomFh": "'3-131'",
			"roomSzc": "1",
			"roomGpdj": "5000",
			"roomGpshdj": "0",
			"roomJzmj": "15.02",
			"roomTnjzmj": "14.57",
			"roomFtmj": "0.45",
			"dj": "0"
		},
		{
			"roomFh": "'3-132'",
			"roomSzc": "1",
			"roomGpdj": "5000",
			"roomGpshdj": "0",
			"roomJzmj": "16.73",
			"roomTnjzmj": "16.23",
			"roomFtmj": "0.5",
			"dj": "0"
		},
		{
			"roomFh": "'4-116'",
			"roomSzc": "1",
			"roomGpdj": "5000",
			"roomGpshdj": "0",
			"roomJzmj": "22.37",
			"roomTnjzmj": "21.7",
			"roomFtmj": "0.67",
			"dj": "0"
		},
		{
			"roomFh": "'4-117'",
			"roomSzc": "1",
			"roomGpdj": "5000",
			"roomGpshdj": "0",
			"roomJzmj": "24.28",
			"roomTnjzmj": "23.56",
			"roomFtmj": "0.72",
			"dj": "0"
		},
		{
			"roomFh": "'4-118'",
			"roomSzc": "1",
			"roomGpdj": "5000",
			"roomGpshdj": "0",
			"roomJzmj": "16.61",
			"roomTnjzmj": "16.12",
			"roomFtmj": "0.49",
			"dj": "0"
		},
		{
			"roomFh": "'4-119'",
			"roomSzc": "1",
			"roomGpdj": "5000",
			"roomGpshdj": "0",
			"roomJzmj": "24.28",
			"roomTnjzmj": "23.56",
			"roomFtmj": "0.72",
			"dj": "0"
		},
		{
			"roomFh": "'4-120'",
			"roomSzc": "1",
			"roomGpdj": "5000",
			"roomGpshdj": "0",
			"roomJzmj": "21.09",
			"roomTnjzmj": "20.46",
			"roomFtmj": "0.63",
			"dj": "0"
		},
		{
			"roomFh": "'4-133'",
			"roomSzc": "1",
			"roomGpdj": "5000",
			"roomGpshdj": "0",
			"roomJzmj": "17.21",
			"roomTnjzmj": "16.7",
			"roomFtmj": "0.51",
			"dj": "0"
		},
		{
			"roomFh": "'4-134'",
			"roomSzc": "1",
			"roomGpdj": "5000",
			"roomGpshdj": "0",
			"roomJzmj": "15.02",
			"roomTnjzmj": "14.57",
			"roomFtmj": "0.45",
			"dj": "0"
		},
		{
			"roomFh": "'4-135'",
			"roomSzc": "1",
			"roomGpdj": "5000",
			"roomGpshdj": "0",
			"roomJzmj": "18.41",
			"roomTnjzmj": "17.86",
			"roomFtmj": "0.55",
			"dj": "0"
		},
		{
			"roomFh": "'4-136'",
			"roomSzc": "1",
			"roomGpdj": "5000",
			"roomGpshdj": "0",
			"roomJzmj": "15.99",
			"roomTnjzmj": "15.51",
			"roomFtmj": "0.48",
			"dj": "0"
		},
		{
			"roomFh": "'1-201'",
			"roomSzc": "2",
			"roomSzdy": "'1'",
			"roomGpdj": "2520",
			"roomGpshdj": "0",
			"roomJzmj": "108.15",
			"roomTnjzmj": "92.33",
			"roomFtmj": "15.82",
			"dj": "0"
		},
		{
			"roomFh": "'1-202'",
			"roomSzc": "2",
			"roomSzdy": "'1'",
			"roomHtbah": "'361026202200061'",
			"roomGpdj": "2520",
			"roomGpshdj": "0",
			"roomJzmj": "91.11",
			"roomTnjzmj": "77.78",
			"roomFtmj": "13.33",
			"dj": "1321.21"
		},
		{
			"roomFh": "'2-203'",
			"roomSzc": "2",
			"roomSzdy": "'2'",
			"roomGpdj": "2520",
			"roomGpshdj": "0",
			"roomJzmj": "104.14",
			"roomTnjzmj": "88.91",
			"roomFtmj": "15.23",
			"dj": "0"
		},
		{
			"roomFh": "'2-204'",
			"roomSzc": "2",
			"roomSzdy": "'2'",
			"roomHtbah": "'361026202200150'",
			"roomGpdj": "2520",
			"roomGpshdj": "0",
			"roomJzmj": "78.45",
			"roomTnjzmj": "66.97",
			"roomFtmj": "11.48",
			"dj": "2171.99"
		},
		{
			"roomFh": "'3-205'",
			"roomSzc": "2",
			"roomSzdy": "'3'",
			"roomHtbah": "'361026202200186'",
			"roomGpdj": "2520",
			"roomGpshdj": "0",
			"roomJzmj": "78.45",
			"roomTnjzmj": "66.97",
			"roomFtmj": "11.48",
			"dj": "2171.99"
		},
		{
			"roomFh": "'3-206'",
			"roomSzc": "2",
			"roomSzdy": "'3'",
			"roomGpdj": "2520",
			"roomGpshdj": "0",
			"roomJzmj": "104.14",
			"roomTnjzmj": "88.91",
			"roomFtmj": "15.23",
			"dj": "0"
		},
		{
			"roomFh": "'4-207'",
			"roomSzc": "2",
			"roomSzdy": "'4'",
			"roomHtbah": "'361026202200067'",
			"roomGpdj": "2520",
			"roomGpshdj": "0",
			"roomJzmj": "91.11",
			"roomTnjzmj": "77.78",
			"roomFtmj": "13.33",
			"dj": "1321.21"
		},
		{
			"roomFh": "'4-208'",
			"roomSzc": "2",
			"roomSzdy": "'4'",
			"roomGpdj": "2520",
			"roomGpshdj": "0",
			"roomJzmj": "108.15",
			"roomTnjzmj": "92.33",
			"roomFtmj": "15.82",
			"dj": "0"
		},
		{
			"roomFh": "'1-301'",
			"roomSzc": "3",
			"roomSzdy": "'1'",
			"roomHtbah": "'162021018522'",
			"roomGpdj": "2680",
			"roomGpshdj": "0",
			"roomJzmj": "108.15",
			"roomTnjzmj": "92.33",
			"roomFtmj": "15.82",
			"dj": "1851.85"
		},
		{
			"roomFh": "'1-302'",
			"roomSzc": "3",
			"roomSzdy": "'1'",
			"roomHtbah": "'361026202200060'",
			"roomGpdj": "2680",
			"roomGpshdj": "0",
			"roomJzmj": "91.11",
			"roomTnjzmj": "77.78",
			"roomFtmj": "13.33",
			"dj": "1321.21"
		},
		{
			"roomFh": "'2-303'",
			"roomSzc": "3",
			"roomSzdy": "'2'",
			"roomGpdj": "2680",
			"roomGpshdj": "0",
			"roomJzmj": "104.14",
			"roomTnjzmj": "88.91",
			"roomFtmj": "15.23",
			"dj": "0"
		},
		{
			"roomFh": "'2-304'",
			"roomSzc": "3",
			"roomSzdy": "'2'",
			"roomHtbah": "'361026202200191'",
			"roomGpdj": "2680",
			"roomGpshdj": "0",
			"roomJzmj": "78.45",
			"roomTnjzmj": "66.97",
			"roomFtmj": "11.48",
			"dj": "2171.99"
		},
		{
			"roomFh": "'3-305'",
			"roomSzc": "3",
			"roomSzdy": "'3'",
			"roomHtbah": "'361026202200183'",
			"roomGpdj": "2680",
			"roomGpshdj": "0",
			"roomJzmj": "78.45",
			"roomTnjzmj": "66.97",
			"roomFtmj": "11.48",
			"dj": "2171.99"
		},
		{
			"roomFh": "'3-306'",
			"roomSzc": "3",
			"roomSzdy": "'3'",
			"roomGpdj": "2680",
			"roomGpshdj": "0",
			"roomJzmj": "104.14",
			"roomTnjzmj": "88.91",
			"roomFtmj": "15.23",
			"dj": "0"
		},
		{
			"roomFh": "'4-307'",
			"roomSzc": "3",
			"roomSzdy": "'4'",
			"roomGpdj": "2680",
			"roomGpshdj": "0",
			"roomJzmj": "91.11",
			"roomTnjzmj": "77.78",
			"roomFtmj": "13.33",
			"dj": "0"
		},
		{
			"roomFh": "'4-308'",
			"roomSzc": "3",
			"roomSzdy": "'4'",
			"roomGpdj": "2680",
			"roomGpshdj": "0",
			"roomJzmj": "108.15",
			"roomTnjzmj": "92.33",
			"roomFtmj": "15.82",
			"dj": "0"
		},
		{
			"roomFh": "'1-401'",
			"roomSzc": "4",
			"roomSzdy": "'1'",
			"roomGpdj": "2680",
			"roomGpshdj": "0",
			"roomJzmj": "108.15",
			"roomTnjzmj": "92.33",
			"roomFtmj": "15.82",
			"dj": "0"
		},
		{
			"roomFh": "'1-402'",
			"roomSzc": "4",
			"roomSzdy": "'1'",
			"roomHtbah": "'361026202200059'",
			"roomGpdj": "2680",
			"roomGpshdj": "0",
			"roomJzmj": "91.11",
			"roomTnjzmj": "77.78",
			"roomFtmj": "13.33",
			"dj": "1321.21"
		},
		{
			"roomFh": "'2-403'",
			"roomSzc": "4",
			"roomSzdy": "'2'",
			"roomHtbah": "'361026202200063'",
			"roomGpdj": "2680",
			"roomGpshdj": "0",
			"roomJzmj": "104.14",
			"roomTnjzmj": "88.91",
			"roomFtmj": "15.23",
			"dj": "1321.2"
		},
		{
			"roomFh": "'2-404'",
			"roomSzc": "4",
			"roomSzdy": "'2'",
			"roomHtbah": "'361026202200190'",
			"roomGpdj": "2680",
			"roomGpshdj": "0",
			"roomJzmj": "78.45",
			"roomTnjzmj": "66.97",
			"roomFtmj": "11.48",
			"dj": "2171.99"
		},
		{
			"roomFh": "'3-405'",
			"roomSzc": "4",
			"roomSzdy": "'3'",
			"roomHtbah": "'361026202200184'",
			"roomGpdj": "2680",
			"roomGpshdj": "0",
			"roomJzmj": "78.45",
			"roomTnjzmj": "66.97",
			"roomFtmj": "11.48",
			"dj": "2171.99"
		},
		{
			"roomFh": "'3-406'",
			"roomSzc": "4",
			"roomSzdy": "'3'",
			"roomGpdj": "2680",
			"roomGpshdj": "0",
			"roomJzmj": "104.14",
			"roomTnjzmj": "88.91",
			"roomFtmj": "15.23",
			"dj": "0"
		},
		{
			"roomFh": "'4-407'",
			"roomSzc": "4",
			"roomSzdy": "'4'",
			"roomHtbah": "'361026202200066'",
			"roomGpdj": "2680",
			"roomGpshdj": "0",
			"roomJzmj": "91.11",
			"roomTnjzmj": "77.78",
			"roomFtmj": "13.33",
			"dj": "1321.21"
		},
		{
			"roomFh": "'4-408'",
			"roomSzc": "4",
			"roomSzdy": "'4'",
			"roomGpdj": "2680",
			"roomGpshdj": "0",
			"roomJzmj": "108.15",
			"roomTnjzmj": "92.33",
			"roomFtmj": "15.82",
			"dj": "0"
		},
		{
			"roomFh": "'1-501'",
			"roomSzc": "5",
			"roomSzdy": "'1'",
			"roomHtbah": "'361026202200058'",
			"roomGpdj": "2520",
			"roomGpshdj": "0",
			"roomJzmj": "108.15",
			"roomTnjzmj": "92.33",
			"roomFtmj": "15.82",
			"dj": "1321.2"
		},
		{
			"roomFh": "'1-502'",
			"roomSzc": "5",
			"roomSzdy": "'1'",
			"roomHtbah": "'361026202200057'",
			"roomGpdj": "2520",
			"roomGpshdj": "0",
			"roomJzmj": "91.11",
			"roomTnjzmj": "77.78",
			"roomFtmj": "13.33",
			"dj": "1321.21"
		},
		{
			"roomFh": "'2-503'",
			"roomSzc": "5",
			"roomSzdy": "'2'",
			"roomHtbah": "'361026202200062'",
			"roomGpdj": "2520",
			"roomGpshdj": "0",
			"roomJzmj": "104.14",
			"roomTnjzmj": "88.91",
			"roomFtmj": "15.23",
			"dj": "1321.2"
		},
		{
			"roomFh": "'2-504'",
			"roomSzc": "5",
			"roomSzdy": "'2'",
			"roomHtbah": "'361026202200187'",
			"roomGpdj": "2520",
			"roomGpshdj": "0",
			"roomJzmj": "78.45",
			"roomTnjzmj": "66.97",
			"roomFtmj": "11.48",
			"dj": "2171.99"
		},
		{
			"roomFh": "'3-505'",
			"roomSzc": "5",
			"roomSzdy": "'3'",
			"roomHtbah": "'361026202200232'",
			"roomGpdj": "2520",
			"roomGpshdj": "0",
			"roomJzmj": "78.45",
			"roomTnjzmj": "66.97",
			"roomFtmj": "11.48",
			"dj": "2171.99"
		},
		{
			"roomFh": "'3-506'",
			"roomSzc": "5",
			"roomSzdy": "'3'",
			"roomHtbah": "'361026202200064'",
			"roomGpdj": "2520",
			"roomGpshdj": "0",
			"roomJzmj": "104.14",
			"roomTnjzmj": "88.91",
			"roomFtmj": "15.23",
			"dj": "1321.2"
		},
		{
			"roomFh": "'4-507'",
			"roomSzc": "5",
			"roomSzdy": "'4'",
			"roomHtbah": "'361026202200065'",
			"roomGpdj": "2520",
			"roomGpshdj": "0",
			"roomJzmj": "91.11",
			"roomTnjzmj": "77.78",
			"roomFtmj": "13.33",
			"dj": "1321.21"
		},
		{
			"roomFh": "'4-508'",
			"roomSzc": "5",
			"roomSzdy": "'4'",
			"roomHtbah": "'361026202200068'",
			"roomGpdj": "2520",
			"roomGpshdj": "0",
			"roomJzmj": "108.15",
			"roomTnjzmj": "92.33",
			"roomFtmj": "15.82",
			"dj": "1321.2"
		}
	]
}